<document title="Changing the default history size" output="studio">
	<meta_data>
		<help>
			<meta>
				<meta_content>history size, change</meta_content>
				<name>MS-HKWD</name>
			</meta>
		</help>
	</meta_data>
	<paragraph>
	By default, there may not be more than 10 items in the history of a development window. It means that combo boxes in the 
		<link>
			<url>../../reference/10_browsing_tools/10_address_bars/10_main_address_bar.xml</url>
			<label>address bar</label>
		</link> will let you choose between at most 10 possibilities. You can change this number.
		<paragraph>To do so, use the 
			<link>
				<url>../../reference/85_preferences/10_overview.xml</url>
				<label>preference window</label>
			</link>: select 
			<bold>Preferences</bold> in the 
			<bold>Tools</bold> menu. Then in the preferences tree, select the "Browsing tools "sub-category in the "Tools" category. On the right part of the window, a list of preferences will appear, including "number of items displayed in the history combo boxes". Click on this item and enter the new value.
		</paragraph>
		<paragraph>Click on 
			<bold>save and exit</bold> to complete the change.
		</paragraph>
		<seealso>
			<bold>See Also</bold>
			<line_break/>
			<link>
				<url>../../reference/85_preferences/10_overview.xml</url>
				<label>Preference window description</label>
			</link>
			<line_break/>
			<link>
				<url>../../reference/85_preferences/00_introduction.xml</url>
				<label>Preferences reference</label>
			</link>
		</seealso>
	</paragraph></document>
