<!DOCTYPE type SYSTEM "../type.dtd">
<class>
	<header>
		<modified>False</modified>
		<frozen>False</frozen>
		<expanded>False</expanded>
		<deferred>False</deferred>
		<generic>False</generic>
		<class_eiffel_name>SYSTEM_WEB_UI_HTMLTEXTWRITER</class_eiffel_name>
		<alias>
			<simple_name>HtmlTextWriter</simple_name>
			<namespace>System.Web.UI</namespace>
			<assembly_name>System.Web</assembly_name>
			<assembly_version>1.0.2411.0</assembly_version>
			<assembly_culture>neutral</assembly_culture>
			<assembly_public_key>b03f5f7f11d50a3a</assembly_public_key>
		</alias>
		<inherit>
			<parent>
				<parent_name>SYSTEM_IDISPOSABLE</parent_name>
				<rename>dispose as system_idisposable_dispose</rename>
			</parent>
			<parent>
				<parent_name>SYSTEM_IO_TEXTWRITER</parent_name>
				<redefine>write_line_string_array_object, write_line_string_object_object, write_line_string_object, write_line_object, write_line_string, write_line_double, write_line_single, write_line_int64, write_line_int32, write_line_boolean, write_line_array_char_int32, write_line_array_char, write_line_char, write_line, write_string_array_object, write_string_object_object, write_string_object, write_object, write_string, write_double, write_single, write, write_int32, write_boolean, write_array_char_int32, write_array_char, write_char, set_new_line, get_new_line, flush, close</redefine>
			</parent>
		</inherit>
		<create_none>False</create_none>
	</header>
	<body>
		<initialization>
			<feature>
				<feature_modified>False</feature_modified>
				<frozen_feature>True</frozen_feature>
				<static>False</static>
				<abstract>False</abstract>
				<method>False</method>
				<field>False</field>
				<creation_routine>True</creation_routine>
				<prefix>False</prefix>
				<infix>False</infix>
				<new_slot>False</new_slot>
				<enum_literal>False</enum_literal>
				<is_literal>False</is_literal>
				<feature_eiffel_name>make_htmltextwriter</feature_eiffel_name>
				<arguments>
					<argument>
						<argument_eiffel_name>writer</argument_eiffel_name>
						<argument_external_name>writer</argument_external_name>
						<argument_type>SYSTEM_IO_TEXTWRITER</argument_type>
						<argument_type_full_name>System.IO.TextWriter</argument_type_full_name>
					</argument>
				</arguments>
			</feature>
			<feature>
				<feature_modified>False</feature_modified>
				<frozen_feature>True</frozen_feature>
				<static>False</static>
				<abstract>False</abstract>
				<method>False</method>
				<field>False</field>
				<creation_routine>True</creation_routine>
				<prefix>False</prefix>
				<infix>False</infix>
				<new_slot>False</new_slot>
				<enum_literal>False</enum_literal>
				<is_literal>False</is_literal>
				<feature_eiffel_name>make_htmltextwriter_1</feature_eiffel_name>
				<arguments>
					<argument>
						<argument_eiffel_name>writer</argument_eiffel_name>
						<argument_external_name>writer</argument_external_name>
						<argument_type>SYSTEM_IO_TEXTWRITER</argument_type>
						<argument_type_full_name>System.IO.TextWriter</argument_type_full_name>
					</argument>
					<argument>
						<argument_eiffel_name>tab_string</argument_eiffel_name>
						<argument_external_name>tabString</argument_external_name>
						<argument_type>STRING</argument_type>
						<argument_type_full_name>System.String</argument_type_full_name>
					</argument>
				</arguments>
			</feature>
		</initialization>
		<access>
			<feature>
				<feature_modified>False</feature_modified>
				<frozen_feature>False</frozen_feature>
				<static>False</static>
				<abstract>False</abstract>
				<method>True</method>
				<field>False</field>
				<creation_routine>False</creation_routine>
				<prefix>False</prefix>
				<infix>False</infix>
				<new_slot>False</new_slot>
				<enum_literal>False</enum_literal>
				<is_literal>False</is_literal>
				<feature_eiffel_name>get_new_line</feature_eiffel_name>
				<feature_external_name>get_NewLine</feature_external_name>
				<return_type>STRING</return_type>
				<return_type_full_name>System.String</return_type_full_name>
			</feature>
			<feature>
				<feature_modified>False</feature_modified>
				<frozen_feature>True</frozen_feature>
				<static>True</static>
				<abstract>False</abstract>
				<method>False</method>
				<field>True</field>
				<creation_routine>False</creation_routine>
				<prefix>False</prefix>
				<infix>False</infix>
				<new_slot>True</new_slot>
				<enum_literal>False</enum_literal>
				<is_literal>True</is_literal>
				<feature_eiffel_name>tag_right_char</feature_eiffel_name>
				<feature_external_name>TagRightChar</feature_external_name>
				<return_type>CHARACTER</return_type>
				<return_type_full_name>System.Char</return_type_full_name>
				<literal_value> '&gt;'</literal_value>
			</feature>
			<feature>
				<feature_modified>False</feature_modified>
				<frozen_feature>True</frozen_feature>
				<static>True</static>
				<abstract>False</abstract>
				<method>False</method>
				<field>True</field>
				<creation_routine>False</creation_routine>
				<prefix>False</prefix>
				<infix>False</infix>
				<new_slot>True</new_slot>
				<enum_literal>False</enum_literal>
				<is_literal>True</is_literal>
				<feature_eiffel_name>equals_char</feature_eiffel_name>
				<feature_external_name>EqualsChar</feature_external_name>
				<return_type>CHARACTER</return_type>
				<return_type_full_name>System.Char</return_type_full_name>
				<literal_value> '='</literal_value>
			</feature>
			<feature>
				<feature_modified>False</feature_modified>
				<frozen_feature>True</frozen_feature>
				<static>True</static>
				<abstract>False</abstract>
				<method>False</method>
				<field>True</field>
				<creation_routine>False</creation_routine>
				<prefix>False</prefix>
				<infix>False</infix>
				<new_slot>True</new_slot>
				<enum_literal>False</enum_literal>
				<is_literal>True</is_literal>
				<feature_eiffel_name>semicolon_char</feature_eiffel_name>
				<feature_external_name>SemicolonChar</feature_external_name>
				<return_type>CHARACTER</return_type>
				<return_type_full_name>System.Char</return_type_full_name>
				<literal_value> ';'</literal_value>
			</feature>
			<feature>
				<feature_modified>False</feature_modified>
				<frozen_feature>True</frozen_feature>
				<static>False</static>
				<abstract>False</abstract>
				<method>True</method>
				<field>False</field>
				<creation_routine>False</creation_routine>
				<prefix>False</prefix>
				<infix>False</infix>
				<new_slot>True</new_slot>
				<enum_literal>False</enum_literal>
				<is_literal>False</is_literal>
				<feature_eiffel_name>get_indent</feature_eiffel_name>
				<feature_external_name>get_Indent</feature_external_name>
				<return_type>INTEGER</return_type>
				<return_type_full_name>System.Int32</return_type_full_name>
			</feature>
			<feature>
				<feature_modified>False</feature_modified>
				<frozen_feature>True</frozen_feature>
				<static>True</static>
				<abstract>False</abstract>
				<method>False</method>
				<field>True</field>
				<creation_routine>False</creation_routine>
				<prefix>False</prefix>
				<infix>False</infix>
				<new_slot>True</new_slot>
				<enum_literal>False</enum_literal>
				<is_literal>True</is_literal>
				<feature_eiffel_name>tag_left_char</feature_eiffel_name>
				<feature_external_name>TagLeftChar</feature_external_name>
				<return_type>CHARACTER</return_type>
				<return_type_full_name>System.Char</return_type_full_name>
				<literal_value> '&lt;'</literal_value>
			</feature>
			<feature>
				<feature_modified>False</feature_modified>
				<frozen_feature>True</frozen_feature>
				<static>True</static>
				<abstract>False</abstract>
				<method>False</method>
				<field>True</field>
				<creation_routine>False</creation_routine>
				<prefix>False</prefix>
				<infix>False</infix>
				<new_slot>True</new_slot>
				<enum_literal>False</enum_literal>
				<is_literal>True</is_literal>
				<feature_eiffel_name>double_quote_char</feature_eiffel_name>
				<feature_external_name>DoubleQuoteChar</feature_external_name>
				<return_type>CHARACTER</return_type>
				<return_type_full_name>System.Char</return_type_full_name>
				<literal_value> '"'</literal_value>
			</feature>
			<feature>
				<feature_modified>False</feature_modified>
				<frozen_feature>True</frozen_feature>
				<static>True</static>
				<abstract>False</abstract>
				<method>False</method>
				<field>True</field>
				<creation_routine>False</creation_routine>
				<prefix>False</prefix>
				<infix>False</infix>
				<new_slot>True</new_slot>
				<enum_literal>False</enum_literal>
				<is_literal>True</is_literal>
				<feature_eiffel_name>slash_char</feature_eiffel_name>
				<feature_external_name>SlashChar</feature_external_name>
				<return_type>CHARACTER</return_type>
				<return_type_full_name>System.Char</return_type_full_name>
				<literal_value> '/'</literal_value>
			</feature>
			<feature>
				<feature_modified>False</feature_modified>
				<frozen_feature>True</frozen_feature>
				<static>True</static>
				<abstract>False</abstract>
				<method>False</method>
				<field>True</field>
				<creation_routine>False</creation_routine>
				<prefix>False</prefix>
				<infix>False</infix>
				<new_slot>True</new_slot>
				<enum_literal>False</enum_literal>
				<is_literal>True</is_literal>
				<feature_eiffel_name>style_equals_char</feature_eiffel_name>
				<feature_external_name>StyleEqualsChar</feature_external_name>
				<return_type>CHARACTER</return_type>
				<return_type_full_name>System.Char</return_type_full_name>
				<literal_value> ':'</literal_value>
			</feature>
			<feature>
				<feature_modified>False</feature_modified>
				<frozen_feature>False</frozen_feature>
				<static>False</static>
				<abstract>False</abstract>
				<method>True</method>
				<field>False</field>
				<creation_routine>False</creation_routine>
				<prefix>False</prefix>
				<infix>False</infix>
				<new_slot>False</new_slot>
				<enum_literal>False</enum_literal>
				<is_literal>False</is_literal>
				<feature_eiffel_name>get_encoding</feature_eiffel_name>
				<feature_external_name>get_Encoding</feature_external_name>
				<return_type>SYSTEM_TEXT_ENCODING</return_type>
				<return_type_full_name>System.Text.Encoding</return_type_full_name>
			</feature>
			<feature>
				<feature_modified>False</feature_modified>
				<frozen_feature>True</frozen_feature>
				<static>True</static>
				<abstract>False</abstract>
				<method>False</method>
				<field>True</field>
				<creation_routine>False</creation_routine>
				<prefix>False</prefix>
				<infix>False</infix>
				<new_slot>True</new_slot>
				<enum_literal>False</enum_literal>
				<is_literal>True</is_literal>
				<feature_eiffel_name>single_quote_char</feature_eiffel_name>
				<feature_external_name>SingleQuoteChar</feature_external_name>
				<return_type>CHARACTER</return_type>
				<return_type_full_name>System.Char</return_type_full_name>
				<literal_value> '''</literal_value>
			</feature>
			<feature>
				<feature_modified>False</feature_modified>
				<frozen_feature>True</frozen_feature>
				<static>False</static>
				<abstract>False</abstract>
				<method>True</method>
				<field>False</field>
				<creation_routine>False</creation_routine>
				<prefix>False</prefix>
				<infix>False</infix>
				<new_slot>True</new_slot>
				<enum_literal>False</enum_literal>
				<is_literal>False</is_literal>
				<feature_eiffel_name>get_inner_writer</feature_eiffel_name>
				<feature_external_name>get_InnerWriter</feature_external_name>
				<return_type>SYSTEM_IO_TEXTWRITER</return_type>
				<return_type_full_name>System.IO.TextWriter</return_type_full_name>
			</feature>
			<feature>
				<feature_modified>False</feature_modified>
				<frozen_feature>True</frozen_feature>
				<static>True</static>
				<abstract>False</abstract>
				<method>False</method>
				<field>True</field>
				<creation_routine>False</creation_routine>
				<prefix>False</prefix>
				<infix>False</infix>
				<new_slot>True</new_slot>
				<enum_literal>False</enum_literal>
				<is_literal>True</is_literal>
				<feature_eiffel_name>space_char</feature_eiffel_name>
				<feature_external_name>SpaceChar</feature_external_name>
				<return_type>CHARACTER</return_type>
				<return_type_full_name>System.Char</return_type_full_name>
				<literal_value> ' '</literal_value>
			</feature>
		</access>
		<element_change>
			<feature>
				<feature_modified>False</feature_modified>
				<frozen_feature>False</frozen_feature>
				<static>False</static>
				<abstract>False</abstract>
				<method>True</method>
				<field>False</field>
				<creation_routine>False</creation_routine>
				<prefix>False</prefix>
				<infix>False</infix>
				<new_slot>False</new_slot>
				<enum_literal>False</enum_literal>
				<is_literal>False</is_literal>
				<feature_eiffel_name>set_new_line</feature_eiffel_name>
				<feature_external_name>set_NewLine</feature_external_name>
				<arguments>
					<argument>
						<argument_eiffel_name>value</argument_eiffel_name>
						<argument_external_name>value</argument_external_name>
						<argument_type>STRING</argument_type>
						<argument_type_full_name>System.String</argument_type_full_name>
					</argument>
				</arguments>
				<return_type />
				<return_type_full_name>System.Void</return_type_full_name>
			</feature>
			<feature>
				<feature_modified>False</feature_modified>
				<frozen_feature>True</frozen_feature>
				<static>False</static>
				<abstract>False</abstract>
				<method>True</method>
				<field>False</field>
				<creation_routine>False</creation_routine>
				<prefix>False</prefix>
				<infix>False</infix>
				<new_slot>True</new_slot>
				<enum_literal>False</enum_literal>
				<is_literal>False</is_literal>
				<feature_eiffel_name>set_indent</feature_eiffel_name>
				<feature_external_name>set_Indent</feature_external_name>
				<arguments>
					<argument>
						<argument_eiffel_name>value</argument_eiffel_name>
						<argument_external_name>value</argument_external_name>
						<argument_type>INTEGER</argument_type>
						<argument_type_full_name>System.Int32</argument_type_full_name>
					</argument>
				</arguments>
				<return_type />
				<return_type_full_name>System.Void</return_type_full_name>
			</feature>
			<feature>
				<feature_modified>False</feature_modified>
				<frozen_feature>True</frozen_feature>
				<static>False</static>
				<abstract>False</abstract>
				<method>True</method>
				<field>False</field>
				<creation_routine>False</creation_routine>
				<prefix>False</prefix>
				<infix>False</infix>
				<new_slot>True</new_slot>
				<enum_literal>False</enum_literal>
				<is_literal>False</is_literal>
				<feature_eiffel_name>set_inner_writer</feature_eiffel_name>
				<feature_external_name>set_InnerWriter</feature_external_name>
				<arguments>
					<argument>
						<argument_eiffel_name>value</argument_eiffel_name>
						<argument_external_name>value</argument_external_name>
						<argument_type>SYSTEM_IO_TEXTWRITER</argument_type>
						<argument_type_full_name>System.IO.TextWriter</argument_type_full_name>
					</argument>
				</arguments>
				<return_type />
				<return_type_full_name>System.Void</return_type_full_name>
			</feature>
		</element_change>
		<basic_operations>
			<feature>
				<feature_modified>False</feature_modified>
				<frozen_feature>False</frozen_feature>
				<static>False</static>
				<abstract>False</abstract>
				<method>True</method>
				<field>False</field>
				<creation_routine>False</creation_routine>
				<prefix>False</prefix>
				<infix>False</infix>
				<new_slot>False</new_slot>
				<enum_literal>False</enum_literal>
				<is_literal>False</is_literal>
				<feature_eiffel_name>write_int32</feature_eiffel_name>
				<feature_external_name>Write</feature_external_name>
				<arguments>
					<argument>
						<argument_eiffel_name>value</argument_eiffel_name>
						<argument_external_name>value</argument_external_name>
						<argument_type>INTEGER</argument_type>
						<argument_type_full_name>System.Int32</argument_type_full_name>
					</argument>
				</arguments>
				<return_type />
				<return_type_full_name>System.Void</return_type_full_name>
			</feature>
			<feature>
				<feature_modified>False</feature_modified>
				<frozen_feature>False</frozen_feature>
				<static>False</static>
				<abstract>False</abstract>
				<method>True</method>
				<field>False</field>
				<creation_routine>False</creation_routine>
				<prefix>False</prefix>
				<infix>False</infix>
				<new_slot>False</new_slot>
				<enum_literal>False</enum_literal>
				<is_literal>False</is_literal>
				<feature_eiffel_name>write_line_int64</feature_eiffel_name>
				<feature_external_name>WriteLine</feature_external_name>
				<arguments>
					<argument>
						<argument_eiffel_name>value</argument_eiffel_name>
						<argument_external_name>value</argument_external_name>
						<argument_type>INTEGER_64</argument_type>
						<argument_type_full_name>System.Int64</argument_type_full_name>
					</argument>
				</arguments>
				<return_type />
				<return_type_full_name>System.Void</return_type_full_name>
			</feature>
			<feature>
				<feature_modified>False</feature_modified>
				<frozen_feature>False</frozen_feature>
				<static>False</static>
				<abstract>False</abstract>
				<method>True</method>
				<field>False</field>
				<creation_routine>False</creation_routine>
				<prefix>False</prefix>
				<infix>False</infix>
				<new_slot>True</new_slot>
				<enum_literal>False</enum_literal>
				<is_literal>False</is_literal>
				<feature_eiffel_name>write_full_begin_tag</feature_eiffel_name>
				<feature_external_name>WriteFullBeginTag</feature_external_name>
				<arguments>
					<argument>
						<argument_eiffel_name>tag_name</argument_eiffel_name>
						<argument_external_name>tagName</argument_external_name>
						<argument_type>STRING</argument_type>
						<argument_type_full_name>System.String</argument_type_full_name>
					</argument>
				</arguments>
				<return_type />
				<return_type_full_name>System.Void</return_type_full_name>
			</feature>
			<feature>
				<feature_modified>False</feature_modified>
				<frozen_feature>False</frozen_feature>
				<static>False</static>
				<abstract>False</abstract>
				<method>True</method>
				<field>False</field>
				<creation_routine>False</creation_routine>
				<prefix>False</prefix>
				<infix>False</infix>
				<new_slot>False</new_slot>
				<enum_literal>False</enum_literal>
				<is_literal>False</is_literal>
				<feature_eiffel_name>write_line</feature_eiffel_name>
				<feature_external_name>WriteLine</feature_external_name>
				<return_type />
				<return_type_full_name>System.Void</return_type_full_name>
			</feature>
			<feature>
				<feature_modified>False</feature_modified>
				<frozen_feature>False</frozen_feature>
				<static>False</static>
				<abstract>False</abstract>
				<method>True</method>
				<field>False</field>
				<creation_routine>False</creation_routine>
				<prefix>False</prefix>
				<infix>False</infix>
				<new_slot>True</new_slot>
				<enum_literal>False</enum_literal>
				<is_literal>False</is_literal>
				<feature_eiffel_name>render_begin_tag</feature_eiffel_name>
				<feature_external_name>RenderBeginTag</feature_external_name>
				<arguments>
					<argument>
						<argument_eiffel_name>tag_name</argument_eiffel_name>
						<argument_external_name>tagName</argument_external_name>
						<argument_type>STRING</argument_type>
						<argument_type_full_name>System.String</argument_type_full_name>
					</argument>
				</arguments>
				<return_type />
				<return_type_full_name>System.Void</return_type_full_name>
			</feature>
			<feature>
				<feature_modified>False</feature_modified>
				<frozen_feature>False</frozen_feature>
				<static>False</static>
				<abstract>False</abstract>
				<method>True</method>
				<field>False</field>
				<creation_routine>False</creation_routine>
				<prefix>False</prefix>
				<infix>False</infix>
				<new_slot>False</new_slot>
				<enum_literal>False</enum_literal>
				<is_literal>False</is_literal>
				<feature_eiffel_name>write_line_char</feature_eiffel_name>
				<feature_external_name>WriteLine</feature_external_name>
				<arguments>
					<argument>
						<argument_eiffel_name>value</argument_eiffel_name>
						<argument_external_name>value</argument_external_name>
						<argument_type>CHARACTER</argument_type>
						<argument_type_full_name>System.Char</argument_type_full_name>
					</argument>
				</arguments>
				<return_type />
				<return_type_full_name>System.Void</return_type_full_name>
			</feature>
			<feature>
				<feature_modified>False</feature_modified>
				<frozen_feature>False</frozen_feature>
				<static>False</static>
				<abstract>False</abstract>
				<method>True</method>
				<field>False</field>
				<creation_routine>False</creation_routine>
				<prefix>False</prefix>
				<infix>False</infix>
				<new_slot>True</new_slot>
				<enum_literal>False</enum_literal>
				<is_literal>False</is_literal>
				<feature_eiffel_name>write_attribute_string_string_boolean</feature_eiffel_name>
				<feature_external_name>WriteAttribute</feature_external_name>
				<arguments>
					<argument>
						<argument_eiffel_name>name</argument_eiffel_name>
						<argument_external_name>name</argument_external_name>
						<argument_type>STRING</argument_type>
						<argument_type_full_name>System.String</argument_type_full_name>
					</argument>
					<argument>
						<argument_eiffel_name>value</argument_eiffel_name>
						<argument_external_name>value</argument_external_name>
						<argument_type>STRING</argument_type>
						<argument_type_full_name>System.String</argument_type_full_name>
					</argument>
					<argument>
						<argument_eiffel_name>f_encode</argument_eiffel_name>
						<argument_external_name>fEncode</argument_external_name>
						<argument_type>BOOLEAN</argument_type>
						<argument_type_full_name>System.Boolean</argument_type_full_name>
					</argument>
				</arguments>
				<return_type />
				<return_type_full_name>System.Void</return_type_full_name>
			</feature>
			<feature>
				<feature_modified>False</feature_modified>
				<frozen_feature>False</frozen_feature>
				<static>False</static>
				<abstract>False</abstract>
				<method>True</method>
				<field>False</field>
				<creation_routine>False</creation_routine>
				<prefix>False</prefix>
				<infix>False</infix>
				<new_slot>False</new_slot>
				<enum_literal>False</enum_literal>
				<is_literal>False</is_literal>
				<feature_eiffel_name>write_line_string_array_object</feature_eiffel_name>
				<feature_external_name>WriteLine</feature_external_name>
				<arguments>
					<argument>
						<argument_eiffel_name>format</argument_eiffel_name>
						<argument_external_name>format</argument_external_name>
						<argument_type>STRING</argument_type>
						<argument_type_full_name>System.String</argument_type_full_name>
					</argument>
					<argument>
						<argument_eiffel_name>arg</argument_eiffel_name>
						<argument_external_name>arg</argument_external_name>
						<argument_type>ARRAY [ANY]</argument_type>
						<argument_type_full_name>System.Object[]</argument_type_full_name>
					</argument>
				</arguments>
				<return_type />
				<return_type_full_name>System.Void</return_type_full_name>
			</feature>
			<feature>
				<feature_modified>False</feature_modified>
				<frozen_feature>False</frozen_feature>
				<static>False</static>
				<abstract>False</abstract>
				<method>True</method>
				<field>False</field>
				<creation_routine>False</creation_routine>
				<prefix>False</prefix>
				<infix>False</infix>
				<new_slot>False</new_slot>
				<enum_literal>False</enum_literal>
				<is_literal>False</is_literal>
				<feature_eiffel_name>write_string_array_object</feature_eiffel_name>
				<feature_external_name>Write</feature_external_name>
				<arguments>
					<argument>
						<argument_eiffel_name>format</argument_eiffel_name>
						<argument_external_name>format</argument_external_name>
						<argument_type>STRING</argument_type>
						<argument_type_full_name>System.String</argument_type_full_name>
					</argument>
					<argument>
						<argument_eiffel_name>arg</argument_eiffel_name>
						<argument_external_name>arg</argument_external_name>
						<argument_type>ARRAY [ANY]</argument_type>
						<argument_type_full_name>System.Object[]</argument_type_full_name>
					</argument>
				</arguments>
				<return_type />
				<return_type_full_name>System.Void</return_type_full_name>
			</feature>
			<feature>
				<feature_modified>False</feature_modified>
				<frozen_feature>False</frozen_feature>
				<static>False</static>
				<abstract>False</abstract>
				<method>True</method>
				<field>False</field>
				<creation_routine>False</creation_routine>
				<prefix>False</prefix>
				<infix>False</infix>
				<new_slot>False</new_slot>
				<enum_literal>False</enum_literal>
				<is_literal>False</is_literal>
				<feature_eiffel_name>write_line_string_object_object</feature_eiffel_name>
				<feature_external_name>WriteLine</feature_external_name>
				<arguments>
					<argument>
						<argument_eiffel_name>format</argument_eiffel_name>
						<argument_external_name>format</argument_external_name>
						<argument_type>STRING</argument_type>
						<argument_type_full_name>System.String</argument_type_full_name>
					</argument>
					<argument>
						<argument_eiffel_name>arg0</argument_eiffel_name>
						<argument_external_name>arg0</argument_external_name>
						<argument_type>ANY</argument_type>
						<argument_type_full_name>System.Object</argument_type_full_name>
					</argument>
					<argument>
						<argument_eiffel_name>arg1</argument_eiffel_name>
						<argument_external_name>arg1</argument_external_name>
						<argument_type>ANY</argument_type>
						<argument_type_full_name>System.Object</argument_type_full_name>
					</argument>
				</arguments>
				<return_type />
				<return_type_full_name>System.Void</return_type_full_name>
			</feature>
			<feature>
				<feature_modified>False</feature_modified>
				<frozen_feature>False</frozen_feature>
				<static>False</static>
				<abstract>False</abstract>
				<method>True</method>
				<field>False</field>
				<creation_routine>False</creation_routine>
				<prefix>False</prefix>
				<infix>False</infix>
				<new_slot>False</new_slot>
				<enum_literal>False</enum_literal>
				<is_literal>False</is_literal>
				<feature_eiffel_name>write_single</feature_eiffel_name>
				<feature_external_name>Write</feature_external_name>
				<arguments>
					<argument>
						<argument_eiffel_name>value</argument_eiffel_name>
						<argument_external_name>value</argument_external_name>
						<argument_type>REAL</argument_type>
						<argument_type_full_name>System.Single</argument_type_full_name>
					</argument>
				</arguments>
				<return_type />
				<return_type_full_name>System.Void</return_type_full_name>
			</feature>
			<feature>
				<feature_modified>False</feature_modified>
				<frozen_feature>False</frozen_feature>
				<static>False</static>
				<abstract>False</abstract>
				<method>True</method>
				<field>False</field>
				<creation_routine>False</creation_routine>
				<prefix>False</prefix>
				<infix>False</infix>
				<new_slot>False</new_slot>
				<enum_literal>False</enum_literal>
				<is_literal>False</is_literal>
				<feature_eiffel_name>write_string</feature_eiffel_name>
				<feature_external_name>Write</feature_external_name>
				<arguments>
					<argument>
						<argument_eiffel_name>s</argument_eiffel_name>
						<argument_external_name>s</argument_external_name>
						<argument_type>STRING</argument_type>
						<argument_type_full_name>System.String</argument_type_full_name>
					</argument>
				</arguments>
				<return_type />
				<return_type_full_name>System.Void</return_type_full_name>
			</feature>
			<feature>
				<feature_modified>False</feature_modified>
				<frozen_feature>False</frozen_feature>
				<static>False</static>
				<abstract>False</abstract>
				<method>True</method>
				<field>False</field>
				<creation_routine>False</creation_routine>
				<prefix>False</prefix>
				<infix>False</infix>
				<new_slot>False</new_slot>
				<enum_literal>False</enum_literal>
				<is_literal>False</is_literal>
				<feature_eiffel_name>write_double</feature_eiffel_name>
				<feature_external_name>Write</feature_external_name>
				<arguments>
					<argument>
						<argument_eiffel_name>value</argument_eiffel_name>
						<argument_external_name>value</argument_external_name>
						<argument_type>DOUBLE</argument_type>
						<argument_type_full_name>System.Double</argument_type_full_name>
					</argument>
				</arguments>
				<return_type />
				<return_type_full_name>System.Void</return_type_full_name>
			</feature>
			<feature>
				<feature_modified>False</feature_modified>
				<frozen_feature>False</frozen_feature>
				<static>False</static>
				<abstract>False</abstract>
				<method>True</method>
				<field>False</field>
				<creation_routine>False</creation_routine>
				<prefix>False</prefix>
				<infix>False</infix>
				<new_slot>True</new_slot>
				<enum_literal>False</enum_literal>
				<is_literal>False</is_literal>
				<feature_eiffel_name>add_style_attribute</feature_eiffel_name>
				<feature_external_name>AddStyleAttribute</feature_external_name>
				<arguments>
					<argument>
						<argument_eiffel_name>name</argument_eiffel_name>
						<argument_external_name>name</argument_external_name>
						<argument_type>STRING</argument_type>
						<argument_type_full_name>System.String</argument_type_full_name>
					</argument>
					<argument>
						<argument_eiffel_name>value</argument_eiffel_name>
						<argument_external_name>value</argument_external_name>
						<argument_type>STRING</argument_type>
						<argument_type_full_name>System.String</argument_type_full_name>
					</argument>
				</arguments>
				<return_type />
				<return_type_full_name>System.Void</return_type_full_name>
			</feature>
			<feature>
				<feature_modified>False</feature_modified>
				<frozen_feature>False</frozen_feature>
				<static>False</static>
				<abstract>False</abstract>
				<method>True</method>
				<field>False</field>
				<creation_routine>False</creation_routine>
				<prefix>False</prefix>
				<infix>False</infix>
				<new_slot>False</new_slot>
				<enum_literal>False</enum_literal>
				<is_literal>False</is_literal>
				<feature_eiffel_name>write</feature_eiffel_name>
				<feature_external_name>Write</feature_external_name>
				<arguments>
					<argument>
						<argument_eiffel_name>value</argument_eiffel_name>
						<argument_external_name>value</argument_external_name>
						<argument_type>INTEGER_64</argument_type>
						<argument_type_full_name>System.Int64</argument_type_full_name>
					</argument>
				</arguments>
				<return_type />
				<return_type_full_name>System.Void</return_type_full_name>
			</feature>
			<feature>
				<feature_modified>False</feature_modified>
				<frozen_feature>False</frozen_feature>
				<static>False</static>
				<abstract>False</abstract>
				<method>True</method>
				<field>False</field>
				<creation_routine>False</creation_routine>
				<prefix>False</prefix>
				<infix>False</infix>
				<new_slot>False</new_slot>
				<enum_literal>False</enum_literal>
				<is_literal>False</is_literal>
				<feature_eiffel_name>write_line_string</feature_eiffel_name>
				<feature_external_name>WriteLine</feature_external_name>
				<arguments>
					<argument>
						<argument_eiffel_name>s</argument_eiffel_name>
						<argument_external_name>s</argument_external_name>
						<argument_type>STRING</argument_type>
						<argument_type_full_name>System.String</argument_type_full_name>
					</argument>
				</arguments>
				<return_type />
				<return_type_full_name>System.Void</return_type_full_name>
			</feature>
			<feature>
				<feature_modified>False</feature_modified>
				<frozen_feature>False</frozen_feature>
				<static>False</static>
				<abstract>False</abstract>
				<method>True</method>
				<field>False</field>
				<creation_routine>False</creation_routine>
				<prefix>False</prefix>
				<infix>False</infix>
				<new_slot>False</new_slot>
				<enum_literal>False</enum_literal>
				<is_literal>False</is_literal>
				<feature_eiffel_name>write_line_single</feature_eiffel_name>
				<feature_external_name>WriteLine</feature_external_name>
				<arguments>
					<argument>
						<argument_eiffel_name>value</argument_eiffel_name>
						<argument_external_name>value</argument_external_name>
						<argument_type>REAL</argument_type>
						<argument_type_full_name>System.Single</argument_type_full_name>
					</argument>
				</arguments>
				<return_type />
				<return_type_full_name>System.Void</return_type_full_name>
			</feature>
			<feature>
				<feature_modified>False</feature_modified>
				<frozen_feature>False</frozen_feature>
				<static>False</static>
				<abstract>False</abstract>
				<method>True</method>
				<field>False</field>
				<creation_routine>False</creation_routine>
				<prefix>False</prefix>
				<infix>False</infix>
				<new_slot>False</new_slot>
				<enum_literal>False</enum_literal>
				<is_literal>False</is_literal>
				<feature_eiffel_name>write_boolean</feature_eiffel_name>
				<feature_external_name>Write</feature_external_name>
				<arguments>
					<argument>
						<argument_eiffel_name>value</argument_eiffel_name>
						<argument_external_name>value</argument_external_name>
						<argument_type>BOOLEAN</argument_type>
						<argument_type_full_name>System.Boolean</argument_type_full_name>
					</argument>
				</arguments>
				<return_type />
				<return_type_full_name>System.Void</return_type_full_name>
			</feature>
			<feature>
				<feature_modified>False</feature_modified>
				<frozen_feature>False</frozen_feature>
				<static>False</static>
				<abstract>False</abstract>
				<method>True</method>
				<field>False</field>
				<creation_routine>False</creation_routine>
				<prefix>False</prefix>
				<infix>False</infix>
				<new_slot>True</new_slot>
				<enum_literal>False</enum_literal>
				<is_literal>False</is_literal>
				<feature_eiffel_name>add_attribute</feature_eiffel_name>
				<feature_external_name>AddAttribute</feature_external_name>
				<arguments>
					<argument>
						<argument_eiffel_name>key</argument_eiffel_name>
						<argument_external_name>key</argument_external_name>
						<argument_type>SYSTEM_WEB_UI_HTMLTEXTWRITERATTRIBUTE</argument_type>
						<argument_type_full_name>System.Web.UI.HtmlTextWriterAttribute</argument_type_full_name>
					</argument>
					<argument>
						<argument_eiffel_name>value</argument_eiffel_name>
						<argument_external_name>value</argument_external_name>
						<argument_type>STRING</argument_type>
						<argument_type_full_name>System.String</argument_type_full_name>
					</argument>
				</arguments>
				<return_type />
				<return_type_full_name>System.Void</return_type_full_name>
			</feature>
			<feature>
				<feature_modified>False</feature_modified>
				<frozen_feature>False</frozen_feature>
				<static>False</static>
				<abstract>False</abstract>
				<method>True</method>
				<field>False</field>
				<creation_routine>False</creation_routine>
				<prefix>False</prefix>
				<infix>False</infix>
				<new_slot>True</new_slot>
				<enum_literal>False</enum_literal>
				<is_literal>False</is_literal>
				<feature_eiffel_name>add_attribute_html_text_writer_attribute_string_boolean</feature_eiffel_name>
				<feature_external_name>AddAttribute</feature_external_name>
				<arguments>
					<argument>
						<argument_eiffel_name>key</argument_eiffel_name>
						<argument_external_name>key</argument_external_name>
						<argument_type>SYSTEM_WEB_UI_HTMLTEXTWRITERATTRIBUTE</argument_type>
						<argument_type_full_name>System.Web.UI.HtmlTextWriterAttribute</argument_type_full_name>
					</argument>
					<argument>
						<argument_eiffel_name>value</argument_eiffel_name>
						<argument_external_name>value</argument_external_name>
						<argument_type>STRING</argument_type>
						<argument_type_full_name>System.String</argument_type_full_name>
					</argument>
					<argument>
						<argument_eiffel_name>f_encode</argument_eiffel_name>
						<argument_external_name>fEncode</argument_external_name>
						<argument_type>BOOLEAN</argument_type>
						<argument_type_full_name>System.Boolean</argument_type_full_name>
					</argument>
				</arguments>
				<return_type />
				<return_type_full_name>System.Void</return_type_full_name>
			</feature>
			<feature>
				<feature_modified>False</feature_modified>
				<frozen_feature>False</frozen_feature>
				<static>False</static>
				<abstract>False</abstract>
				<method>True</method>
				<field>False</field>
				<creation_routine>False</creation_routine>
				<prefix>False</prefix>
				<infix>False</infix>
				<new_slot>True</new_slot>
				<enum_literal>False</enum_literal>
				<is_literal>False</is_literal>
				<feature_eiffel_name>render_end_tag</feature_eiffel_name>
				<feature_external_name>RenderEndTag</feature_external_name>
				<return_type />
				<return_type_full_name>System.Void</return_type_full_name>
			</feature>
			<feature>
				<feature_modified>False</feature_modified>
				<frozen_feature>False</frozen_feature>
				<static>False</static>
				<abstract>False</abstract>
				<method>True</method>
				<field>False</field>
				<creation_routine>False</creation_routine>
				<prefix>False</prefix>
				<infix>False</infix>
				<new_slot>False</new_slot>
				<enum_literal>False</enum_literal>
				<is_literal>False</is_literal>
				<feature_eiffel_name>write_string_object_object</feature_eiffel_name>
				<feature_external_name>Write</feature_external_name>
				<arguments>
					<argument>
						<argument_eiffel_name>format</argument_eiffel_name>
						<argument_external_name>format</argument_external_name>
						<argument_type>STRING</argument_type>
						<argument_type_full_name>System.String</argument_type_full_name>
					</argument>
					<argument>
						<argument_eiffel_name>arg0</argument_eiffel_name>
						<argument_external_name>arg0</argument_external_name>
						<argument_type>ANY</argument_type>
						<argument_type_full_name>System.Object</argument_type_full_name>
					</argument>
					<argument>
						<argument_eiffel_name>arg1</argument_eiffel_name>
						<argument_external_name>arg1</argument_external_name>
						<argument_type>ANY</argument_type>
						<argument_type_full_name>System.Object</argument_type_full_name>
					</argument>
				</arguments>
				<return_type />
				<return_type_full_name>System.Void</return_type_full_name>
			</feature>
			<feature>
				<feature_modified>False</feature_modified>
				<frozen_feature>False</frozen_feature>
				<static>False</static>
				<abstract>False</abstract>
				<method>True</method>
				<field>False</field>
				<creation_routine>False</creation_routine>
				<prefix>False</prefix>
				<infix>False</infix>
				<new_slot>False</new_slot>
				<enum_literal>False</enum_literal>
				<is_literal>False</is_literal>
				<feature_eiffel_name>close</feature_eiffel_name>
				<feature_external_name>Close</feature_external_name>
				<return_type />
				<return_type_full_name>System.Void</return_type_full_name>
			</feature>
			<feature>
				<feature_modified>False</feature_modified>
				<frozen_feature>False</frozen_feature>
				<static>False</static>
				<abstract>False</abstract>
				<method>True</method>
				<field>False</field>
				<creation_routine>False</creation_routine>
				<prefix>False</prefix>
				<infix>False</infix>
				<new_slot>True</new_slot>
				<enum_literal>False</enum_literal>
				<is_literal>False</is_literal>
				<feature_eiffel_name>write_end_tag</feature_eiffel_name>
				<feature_external_name>WriteEndTag</feature_external_name>
				<arguments>
					<argument>
						<argument_eiffel_name>tag_name</argument_eiffel_name>
						<argument_external_name>tagName</argument_external_name>
						<argument_type>STRING</argument_type>
						<argument_type_full_name>System.String</argument_type_full_name>
					</argument>
				</arguments>
				<return_type />
				<return_type_full_name>System.Void</return_type_full_name>
			</feature>
			<feature>
				<feature_modified>False</feature_modified>
				<frozen_feature>False</frozen_feature>
				<static>False</static>
				<abstract>False</abstract>
				<method>True</method>
				<field>False</field>
				<creation_routine>False</creation_routine>
				<prefix>False</prefix>
				<infix>False</infix>
				<new_slot>False</new_slot>
				<enum_literal>False</enum_literal>
				<is_literal>False</is_literal>
				<feature_eiffel_name>write_line_string_object</feature_eiffel_name>
				<feature_external_name>WriteLine</feature_external_name>
				<arguments>
					<argument>
						<argument_eiffel_name>format</argument_eiffel_name>
						<argument_external_name>format</argument_external_name>
						<argument_type>STRING</argument_type>
						<argument_type_full_name>System.String</argument_type_full_name>
					</argument>
					<argument>
						<argument_eiffel_name>arg0</argument_eiffel_name>
						<argument_external_name>arg0</argument_external_name>
						<argument_type>ANY</argument_type>
						<argument_type_full_name>System.Object</argument_type_full_name>
					</argument>
				</arguments>
				<return_type />
				<return_type_full_name>System.Void</return_type_full_name>
			</feature>
			<feature>
				<feature_modified>False</feature_modified>
				<frozen_feature>False</frozen_feature>
				<static>False</static>
				<abstract>False</abstract>
				<method>True</method>
				<field>False</field>
				<creation_routine>False</creation_routine>
				<prefix>False</prefix>
				<infix>False</infix>
				<new_slot>True</new_slot>
				<enum_literal>False</enum_literal>
				<is_literal>False</is_literal>
				<feature_eiffel_name>add_style_attribute_html_text_writer_style</feature_eiffel_name>
				<feature_external_name>AddStyleAttribute</feature_external_name>
				<arguments>
					<argument>
						<argument_eiffel_name>key</argument_eiffel_name>
						<argument_external_name>key</argument_external_name>
						<argument_type>SYSTEM_WEB_UI_HTMLTEXTWRITERSTYLE</argument_type>
						<argument_type_full_name>System.Web.UI.HtmlTextWriterStyle</argument_type_full_name>
					</argument>
					<argument>
						<argument_eiffel_name>value</argument_eiffel_name>
						<argument_external_name>value</argument_external_name>
						<argument_type>STRING</argument_type>
						<argument_type_full_name>System.String</argument_type_full_name>
					</argument>
				</arguments>
				<return_type />
				<return_type_full_name>System.Void</return_type_full_name>
			</feature>
			<feature>
				<feature_modified>False</feature_modified>
				<frozen_feature>False</frozen_feature>
				<static>False</static>
				<abstract>False</abstract>
				<method>True</method>
				<field>False</field>
				<creation_routine>False</creation_routine>
				<prefix>False</prefix>
				<infix>False</infix>
				<new_slot>False</new_slot>
				<enum_literal>False</enum_literal>
				<is_literal>False</is_literal>
				<feature_eiffel_name>write_char</feature_eiffel_name>
				<feature_external_name>Write</feature_external_name>
				<arguments>
					<argument>
						<argument_eiffel_name>value</argument_eiffel_name>
						<argument_external_name>value</argument_external_name>
						<argument_type>CHARACTER</argument_type>
						<argument_type_full_name>System.Char</argument_type_full_name>
					</argument>
				</arguments>
				<return_type />
				<return_type_full_name>System.Void</return_type_full_name>
			</feature>
			<feature>
				<feature_modified>False</feature_modified>
				<frozen_feature>False</frozen_feature>
				<static>False</static>
				<abstract>False</abstract>
				<method>True</method>
				<field>False</field>
				<creation_routine>False</creation_routine>
				<prefix>False</prefix>
				<infix>False</infix>
				<new_slot>True</new_slot>
				<enum_literal>False</enum_literal>
				<is_literal>False</is_literal>
				<feature_eiffel_name>write_begin_tag</feature_eiffel_name>
				<feature_external_name>WriteBeginTag</feature_external_name>
				<arguments>
					<argument>
						<argument_eiffel_name>tag_name</argument_eiffel_name>
						<argument_external_name>tagName</argument_external_name>
						<argument_type>STRING</argument_type>
						<argument_type_full_name>System.String</argument_type_full_name>
					</argument>
				</arguments>
				<return_type />
				<return_type_full_name>System.Void</return_type_full_name>
			</feature>
			<feature>
				<feature_modified>False</feature_modified>
				<frozen_feature>False</frozen_feature>
				<static>False</static>
				<abstract>False</abstract>
				<method>True</method>
				<field>False</field>
				<creation_routine>False</creation_routine>
				<prefix>False</prefix>
				<infix>False</infix>
				<new_slot>False</new_slot>
				<enum_literal>False</enum_literal>
				<is_literal>False</is_literal>
				<feature_eiffel_name>write_array_char_int32</feature_eiffel_name>
				<feature_external_name>Write</feature_external_name>
				<arguments>
					<argument>
						<argument_eiffel_name>buffer</argument_eiffel_name>
						<argument_external_name>buffer</argument_external_name>
						<argument_type>ARRAY [CHARACTER]</argument_type>
						<argument_type_full_name>System.Char[]</argument_type_full_name>
					</argument>
					<argument>
						<argument_eiffel_name>index</argument_eiffel_name>
						<argument_external_name>index</argument_external_name>
						<argument_type>INTEGER</argument_type>
						<argument_type_full_name>System.Int32</argument_type_full_name>
					</argument>
					<argument>
						<argument_eiffel_name>count</argument_eiffel_name>
						<argument_external_name>count</argument_external_name>
						<argument_type>INTEGER</argument_type>
						<argument_type_full_name>System.Int32</argument_type_full_name>
					</argument>
				</arguments>
				<return_type />
				<return_type_full_name>System.Void</return_type_full_name>
			</feature>
			<feature>
				<feature_modified>False</feature_modified>
				<frozen_feature>False</frozen_feature>
				<static>False</static>
				<abstract>False</abstract>
				<method>True</method>
				<field>False</field>
				<creation_routine>False</creation_routine>
				<prefix>False</prefix>
				<infix>False</infix>
				<new_slot>False</new_slot>
				<enum_literal>False</enum_literal>
				<is_literal>False</is_literal>
				<feature_eiffel_name>write_object</feature_eiffel_name>
				<feature_external_name>Write</feature_external_name>
				<arguments>
					<argument>
						<argument_eiffel_name>value</argument_eiffel_name>
						<argument_external_name>value</argument_external_name>
						<argument_type>ANY</argument_type>
						<argument_type_full_name>System.Object</argument_type_full_name>
					</argument>
				</arguments>
				<return_type />
				<return_type_full_name>System.Void</return_type_full_name>
			</feature>
			<feature>
				<feature_modified>False</feature_modified>
				<frozen_feature>False</frozen_feature>
				<static>False</static>
				<abstract>False</abstract>
				<method>True</method>
				<field>False</field>
				<creation_routine>False</creation_routine>
				<prefix>False</prefix>
				<infix>False</infix>
				<new_slot>False</new_slot>
				<enum_literal>False</enum_literal>
				<is_literal>False</is_literal>
				<feature_eiffel_name>write_line_array_char</feature_eiffel_name>
				<feature_external_name>WriteLine</feature_external_name>
				<arguments>
					<argument>
						<argument_eiffel_name>buffer</argument_eiffel_name>
						<argument_external_name>buffer</argument_external_name>
						<argument_type>ARRAY [CHARACTER]</argument_type>
						<argument_type_full_name>System.Char[]</argument_type_full_name>
					</argument>
				</arguments>
				<return_type />
				<return_type_full_name>System.Void</return_type_full_name>
			</feature>
			<feature>
				<feature_modified>False</feature_modified>
				<frozen_feature>False</frozen_feature>
				<static>False</static>
				<abstract>False</abstract>
				<method>True</method>
				<field>False</field>
				<creation_routine>False</creation_routine>
				<prefix>False</prefix>
				<infix>False</infix>
				<new_slot>False</new_slot>
				<enum_literal>False</enum_literal>
				<is_literal>False</is_literal>
				<feature_eiffel_name>write_line_int32</feature_eiffel_name>
				<feature_external_name>WriteLine</feature_external_name>
				<arguments>
					<argument>
						<argument_eiffel_name>value</argument_eiffel_name>
						<argument_external_name>value</argument_external_name>
						<argument_type>INTEGER</argument_type>
						<argument_type_full_name>System.Int32</argument_type_full_name>
					</argument>
				</arguments>
				<return_type />
				<return_type_full_name>System.Void</return_type_full_name>
			</feature>
			<feature>
				<feature_modified>False</feature_modified>
				<frozen_feature>False</frozen_feature>
				<static>False</static>
				<abstract>False</abstract>
				<method>True</method>
				<field>False</field>
				<creation_routine>False</creation_routine>
				<prefix>False</prefix>
				<infix>False</infix>
				<new_slot>True</new_slot>
				<enum_literal>False</enum_literal>
				<is_literal>False</is_literal>
				<feature_eiffel_name>add_attribute_string_string</feature_eiffel_name>
				<feature_external_name>AddAttribute</feature_external_name>
				<arguments>
					<argument>
						<argument_eiffel_name>name</argument_eiffel_name>
						<argument_external_name>name</argument_external_name>
						<argument_type>STRING</argument_type>
						<argument_type_full_name>System.String</argument_type_full_name>
					</argument>
					<argument>
						<argument_eiffel_name>value</argument_eiffel_name>
						<argument_external_name>value</argument_external_name>
						<argument_type>STRING</argument_type>
						<argument_type_full_name>System.String</argument_type_full_name>
					</argument>
				</arguments>
				<return_type />
				<return_type_full_name>System.Void</return_type_full_name>
			</feature>
			<feature>
				<feature_modified>False</feature_modified>
				<frozen_feature>False</frozen_feature>
				<static>False</static>
				<abstract>False</abstract>
				<method>True</method>
				<field>False</field>
				<creation_routine>False</creation_routine>
				<prefix>False</prefix>
				<infix>False</infix>
				<new_slot>False</new_slot>
				<enum_literal>False</enum_literal>
				<is_literal>False</is_literal>
				<feature_eiffel_name>write_line_array_char_int32</feature_eiffel_name>
				<feature_external_name>WriteLine</feature_external_name>
				<arguments>
					<argument>
						<argument_eiffel_name>buffer</argument_eiffel_name>
						<argument_external_name>buffer</argument_external_name>
						<argument_type>ARRAY [CHARACTER]</argument_type>
						<argument_type_full_name>System.Char[]</argument_type_full_name>
					</argument>
					<argument>
						<argument_eiffel_name>index</argument_eiffel_name>
						<argument_external_name>index</argument_external_name>
						<argument_type>INTEGER</argument_type>
						<argument_type_full_name>System.Int32</argument_type_full_name>
					</argument>
					<argument>
						<argument_eiffel_name>count</argument_eiffel_name>
						<argument_external_name>count</argument_external_name>
						<argument_type>INTEGER</argument_type>
						<argument_type_full_name>System.Int32</argument_type_full_name>
					</argument>
				</arguments>
				<return_type />
				<return_type_full_name>System.Void</return_type_full_name>
			</feature>
			<feature>
				<feature_modified>False</feature_modified>
				<frozen_feature>False</frozen_feature>
				<static>False</static>
				<abstract>False</abstract>
				<method>True</method>
				<field>False</field>
				<creation_routine>False</creation_routine>
				<prefix>False</prefix>
				<infix>False</infix>
				<new_slot>True</new_slot>
				<enum_literal>False</enum_literal>
				<is_literal>False</is_literal>
				<feature_eiffel_name>add_attribute_string_string_boolean</feature_eiffel_name>
				<feature_external_name>AddAttribute</feature_external_name>
				<arguments>
					<argument>
						<argument_eiffel_name>name</argument_eiffel_name>
						<argument_external_name>name</argument_external_name>
						<argument_type>STRING</argument_type>
						<argument_type_full_name>System.String</argument_type_full_name>
					</argument>
					<argument>
						<argument_eiffel_name>value</argument_eiffel_name>
						<argument_external_name>value</argument_external_name>
						<argument_type>STRING</argument_type>
						<argument_type_full_name>System.String</argument_type_full_name>
					</argument>
					<argument>
						<argument_eiffel_name>f_endode</argument_eiffel_name>
						<argument_external_name>fEndode</argument_external_name>
						<argument_type>BOOLEAN</argument_type>
						<argument_type_full_name>System.Boolean</argument_type_full_name>
					</argument>
				</arguments>
				<return_type />
				<return_type_full_name>System.Void</return_type_full_name>
			</feature>
			<feature>
				<feature_modified>False</feature_modified>
				<frozen_feature>False</frozen_feature>
				<static>False</static>
				<abstract>False</abstract>
				<method>True</method>
				<field>False</field>
				<creation_routine>False</creation_routine>
				<prefix>False</prefix>
				<infix>False</infix>
				<new_slot>False</new_slot>
				<enum_literal>False</enum_literal>
				<is_literal>False</is_literal>
				<feature_eiffel_name>write_line_boolean</feature_eiffel_name>
				<feature_external_name>WriteLine</feature_external_name>
				<arguments>
					<argument>
						<argument_eiffel_name>value</argument_eiffel_name>
						<argument_external_name>value</argument_external_name>
						<argument_type>BOOLEAN</argument_type>
						<argument_type_full_name>System.Boolean</argument_type_full_name>
					</argument>
				</arguments>
				<return_type />
				<return_type_full_name>System.Void</return_type_full_name>
			</feature>
			<feature>
				<feature_modified>False</feature_modified>
				<frozen_feature>False</frozen_feature>
				<static>False</static>
				<abstract>False</abstract>
				<method>True</method>
				<field>False</field>
				<creation_routine>False</creation_routine>
				<prefix>False</prefix>
				<infix>False</infix>
				<new_slot>False</new_slot>
				<enum_literal>False</enum_literal>
				<is_literal>False</is_literal>
				<feature_eiffel_name>write_array_char</feature_eiffel_name>
				<feature_external_name>Write</feature_external_name>
				<arguments>
					<argument>
						<argument_eiffel_name>buffer</argument_eiffel_name>
						<argument_external_name>buffer</argument_external_name>
						<argument_type>ARRAY [CHARACTER]</argument_type>
						<argument_type_full_name>System.Char[]</argument_type_full_name>
					</argument>
				</arguments>
				<return_type />
				<return_type_full_name>System.Void</return_type_full_name>
			</feature>
			<feature>
				<feature_modified>False</feature_modified>
				<frozen_feature>False</frozen_feature>
				<static>False</static>
				<abstract>False</abstract>
				<method>True</method>
				<field>False</field>
				<creation_routine>False</creation_routine>
				<prefix>False</prefix>
				<infix>False</infix>
				<new_slot>True</new_slot>
				<enum_literal>False</enum_literal>
				<is_literal>False</is_literal>
				<feature_eiffel_name>render_begin_tag_html_text_writer_tag</feature_eiffel_name>
				<feature_external_name>RenderBeginTag</feature_external_name>
				<arguments>
					<argument>
						<argument_eiffel_name>tag_key</argument_eiffel_name>
						<argument_external_name>tagKey</argument_external_name>
						<argument_type>SYSTEM_WEB_UI_HTMLTEXTWRITERTAG</argument_type>
						<argument_type_full_name>System.Web.UI.HtmlTextWriterTag</argument_type_full_name>
					</argument>
				</arguments>
				<return_type />
				<return_type_full_name>System.Void</return_type_full_name>
			</feature>
			<feature>
				<feature_modified>False</feature_modified>
				<frozen_feature>False</frozen_feature>
				<static>False</static>
				<abstract>False</abstract>
				<method>True</method>
				<field>False</field>
				<creation_routine>False</creation_routine>
				<prefix>False</prefix>
				<infix>False</infix>
				<new_slot>True</new_slot>
				<enum_literal>False</enum_literal>
				<is_literal>False</is_literal>
				<feature_eiffel_name>write_style_attribute_string_string_boolean</feature_eiffel_name>
				<feature_external_name>WriteStyleAttribute</feature_external_name>
				<arguments>
					<argument>
						<argument_eiffel_name>name</argument_eiffel_name>
						<argument_external_name>name</argument_external_name>
						<argument_type>STRING</argument_type>
						<argument_type_full_name>System.String</argument_type_full_name>
					</argument>
					<argument>
						<argument_eiffel_name>value</argument_eiffel_name>
						<argument_external_name>value</argument_external_name>
						<argument_type>STRING</argument_type>
						<argument_type_full_name>System.String</argument_type_full_name>
					</argument>
					<argument>
						<argument_eiffel_name>f_encode</argument_eiffel_name>
						<argument_external_name>fEncode</argument_external_name>
						<argument_type>BOOLEAN</argument_type>
						<argument_type_full_name>System.Boolean</argument_type_full_name>
					</argument>
				</arguments>
				<return_type />
				<return_type_full_name>System.Void</return_type_full_name>
			</feature>
			<feature>
				<feature_modified>False</feature_modified>
				<frozen_feature>False</frozen_feature>
				<static>False</static>
				<abstract>False</abstract>
				<method>True</method>
				<field>False</field>
				<creation_routine>False</creation_routine>
				<prefix>False</prefix>
				<infix>False</infix>
				<new_slot>False</new_slot>
				<enum_literal>False</enum_literal>
				<is_literal>False</is_literal>
				<feature_eiffel_name>write_string_object</feature_eiffel_name>
				<feature_external_name>Write</feature_external_name>
				<arguments>
					<argument>
						<argument_eiffel_name>format</argument_eiffel_name>
						<argument_external_name>format</argument_external_name>
						<argument_type>STRING</argument_type>
						<argument_type_full_name>System.String</argument_type_full_name>
					</argument>
					<argument>
						<argument_eiffel_name>arg0</argument_eiffel_name>
						<argument_external_name>arg0</argument_external_name>
						<argument_type>ANY</argument_type>
						<argument_type_full_name>System.Object</argument_type_full_name>
					</argument>
				</arguments>
				<return_type />
				<return_type_full_name>System.Void</return_type_full_name>
			</feature>
			<feature>
				<feature_modified>False</feature_modified>
				<frozen_feature>False</frozen_feature>
				<static>False</static>
				<abstract>False</abstract>
				<method>True</method>
				<field>False</field>
				<creation_routine>False</creation_routine>
				<prefix>False</prefix>
				<infix>False</infix>
				<new_slot>False</new_slot>
				<enum_literal>False</enum_literal>
				<is_literal>False</is_literal>
				<feature_eiffel_name>write_line_double</feature_eiffel_name>
				<feature_external_name>WriteLine</feature_external_name>
				<arguments>
					<argument>
						<argument_eiffel_name>value</argument_eiffel_name>
						<argument_external_name>value</argument_external_name>
						<argument_type>DOUBLE</argument_type>
						<argument_type_full_name>System.Double</argument_type_full_name>
					</argument>
				</arguments>
				<return_type />
				<return_type_full_name>System.Void</return_type_full_name>
			</feature>
			<feature>
				<feature_modified>False</feature_modified>
				<frozen_feature>True</frozen_feature>
				<static>False</static>
				<abstract>False</abstract>
				<method>True</method>
				<field>False</field>
				<creation_routine>False</creation_routine>
				<prefix>False</prefix>
				<infix>False</infix>
				<new_slot>True</new_slot>
				<enum_literal>False</enum_literal>
				<is_literal>False</is_literal>
				<feature_eiffel_name>write_line_no_tabs</feature_eiffel_name>
				<feature_external_name>WriteLineNoTabs</feature_external_name>
				<arguments>
					<argument>
						<argument_eiffel_name>s</argument_eiffel_name>
						<argument_external_name>s</argument_external_name>
						<argument_type>STRING</argument_type>
						<argument_type_full_name>System.String</argument_type_full_name>
					</argument>
				</arguments>
				<return_type />
				<return_type_full_name>System.Void</return_type_full_name>
			</feature>
			<feature>
				<feature_modified>False</feature_modified>
				<frozen_feature>False</frozen_feature>
				<static>False</static>
				<abstract>False</abstract>
				<method>True</method>
				<field>False</field>
				<creation_routine>False</creation_routine>
				<prefix>False</prefix>
				<infix>False</infix>
				<new_slot>True</new_slot>
				<enum_literal>False</enum_literal>
				<is_literal>False</is_literal>
				<feature_eiffel_name>write_style_attribute</feature_eiffel_name>
				<feature_external_name>WriteStyleAttribute</feature_external_name>
				<arguments>
					<argument>
						<argument_eiffel_name>name</argument_eiffel_name>
						<argument_external_name>name</argument_external_name>
						<argument_type>STRING</argument_type>
						<argument_type_full_name>System.String</argument_type_full_name>
					</argument>
					<argument>
						<argument_eiffel_name>value</argument_eiffel_name>
						<argument_external_name>value</argument_external_name>
						<argument_type>STRING</argument_type>
						<argument_type_full_name>System.String</argument_type_full_name>
					</argument>
				</arguments>
				<return_type />
				<return_type_full_name>System.Void</return_type_full_name>
			</feature>
			<feature>
				<feature_modified>False</feature_modified>
				<frozen_feature>False</frozen_feature>
				<static>False</static>
				<abstract>False</abstract>
				<method>True</method>
				<field>False</field>
				<creation_routine>False</creation_routine>
				<prefix>False</prefix>
				<infix>False</infix>
				<new_slot>False</new_slot>
				<enum_literal>False</enum_literal>
				<is_literal>False</is_literal>
				<feature_eiffel_name>write_line_object</feature_eiffel_name>
				<feature_external_name>WriteLine</feature_external_name>
				<arguments>
					<argument>
						<argument_eiffel_name>value</argument_eiffel_name>
						<argument_external_name>value</argument_external_name>
						<argument_type>ANY</argument_type>
						<argument_type_full_name>System.Object</argument_type_full_name>
					</argument>
				</arguments>
				<return_type />
				<return_type_full_name>System.Void</return_type_full_name>
			</feature>
			<feature>
				<feature_modified>False</feature_modified>
				<frozen_feature>False</frozen_feature>
				<static>False</static>
				<abstract>False</abstract>
				<method>True</method>
				<field>False</field>
				<creation_routine>False</creation_routine>
				<prefix>False</prefix>
				<infix>False</infix>
				<new_slot>False</new_slot>
				<enum_literal>False</enum_literal>
				<is_literal>False</is_literal>
				<feature_eiffel_name>flush</feature_eiffel_name>
				<feature_external_name>Flush</feature_external_name>
				<return_type />
				<return_type_full_name>System.Void</return_type_full_name>
			</feature>
			<feature>
				<feature_modified>False</feature_modified>
				<frozen_feature>False</frozen_feature>
				<static>False</static>
				<abstract>False</abstract>
				<method>True</method>
				<field>False</field>
				<creation_routine>False</creation_routine>
				<prefix>False</prefix>
				<infix>False</infix>
				<new_slot>True</new_slot>
				<enum_literal>False</enum_literal>
				<is_literal>False</is_literal>
				<feature_eiffel_name>write_attribute</feature_eiffel_name>
				<feature_external_name>WriteAttribute</feature_external_name>
				<arguments>
					<argument>
						<argument_eiffel_name>name</argument_eiffel_name>
						<argument_external_name>name</argument_external_name>
						<argument_type>STRING</argument_type>
						<argument_type_full_name>System.String</argument_type_full_name>
					</argument>
					<argument>
						<argument_eiffel_name>value</argument_eiffel_name>
						<argument_external_name>value</argument_external_name>
						<argument_type>STRING</argument_type>
						<argument_type_full_name>System.String</argument_type_full_name>
					</argument>
				</arguments>
				<return_type />
				<return_type_full_name>System.Void</return_type_full_name>
			</feature>
		</basic_operations>
		<implementation>
			<feature>
				<feature_modified>False</feature_modified>
				<frozen_feature>True</frozen_feature>
				<static>False</static>
				<abstract>False</abstract>
				<method>True</method>
				<field>False</field>
				<creation_routine>False</creation_routine>
				<prefix>False</prefix>
				<infix>False</infix>
				<new_slot>True</new_slot>
				<enum_literal>False</enum_literal>
				<is_literal>False</is_literal>
				<feature_eiffel_name>encode_url</feature_eiffel_name>
				<feature_external_name>EncodeUrl</feature_external_name>
				<arguments>
					<argument>
						<argument_eiffel_name>url</argument_eiffel_name>
						<argument_external_name>url</argument_external_name>
						<argument_type>STRING</argument_type>
						<argument_type_full_name>System.String</argument_type_full_name>
					</argument>
				</arguments>
				<return_type>STRING</return_type>
				<return_type_full_name>System.String</return_type_full_name>
			</feature>
			<feature>
				<feature_modified>False</feature_modified>
				<frozen_feature>False</frozen_feature>
				<static>False</static>
				<abstract>False</abstract>
				<method>True</method>
				<field>False</field>
				<creation_routine>False</creation_routine>
				<prefix>False</prefix>
				<infix>False</infix>
				<new_slot>True</new_slot>
				<enum_literal>False</enum_literal>
				<is_literal>False</is_literal>
				<feature_eiffel_name>get_tag_key_string</feature_eiffel_name>
				<feature_external_name>GetTagKey</feature_external_name>
				<arguments>
					<argument>
						<argument_eiffel_name>tag_name</argument_eiffel_name>
						<argument_external_name>tagName</argument_external_name>
						<argument_type>STRING</argument_type>
						<argument_type_full_name>System.String</argument_type_full_name>
					</argument>
				</arguments>
				<return_type>SYSTEM_WEB_UI_HTMLTEXTWRITERTAG</return_type>
				<return_type_full_name>System.Web.UI.HtmlTextWriterTag</return_type_full_name>
			</feature>
			<feature>
				<feature_modified>False</feature_modified>
				<frozen_feature>True</frozen_feature>
				<static>False</static>
				<abstract>False</abstract>
				<method>True</method>
				<field>False</field>
				<creation_routine>False</creation_routine>
				<prefix>False</prefix>
				<infix>False</infix>
				<new_slot>True</new_slot>
				<enum_literal>False</enum_literal>
				<is_literal>False</is_literal>
				<feature_eiffel_name>get_style_key</feature_eiffel_name>
				<feature_external_name>GetStyleKey</feature_external_name>
				<arguments>
					<argument>
						<argument_eiffel_name>style_name</argument_eiffel_name>
						<argument_external_name>styleName</argument_external_name>
						<argument_type>STRING</argument_type>
						<argument_type_full_name>System.String</argument_type_full_name>
					</argument>
				</arguments>
				<return_type>SYSTEM_WEB_UI_HTMLTEXTWRITERSTYLE</return_type>
				<return_type_full_name>System.Web.UI.HtmlTextWriterStyle</return_type_full_name>
			</feature>
			<feature>
				<feature_modified>False</feature_modified>
				<frozen_feature>True</frozen_feature>
				<static>False</static>
				<abstract>False</abstract>
				<method>True</method>
				<field>False</field>
				<creation_routine>False</creation_routine>
				<prefix>False</prefix>
				<infix>False</infix>
				<new_slot>True</new_slot>
				<enum_literal>False</enum_literal>
				<is_literal>False</is_literal>
				<feature_eiffel_name>get_attribute_name</feature_eiffel_name>
				<feature_external_name>GetAttributeName</feature_external_name>
				<arguments>
					<argument>
						<argument_eiffel_name>attr_key</argument_eiffel_name>
						<argument_external_name>attrKey</argument_external_name>
						<argument_type>SYSTEM_WEB_UI_HTMLTEXTWRITERATTRIBUTE</argument_type>
						<argument_type_full_name>System.Web.UI.HtmlTextWriterAttribute</argument_type_full_name>
					</argument>
				</arguments>
				<return_type>STRING</return_type>
				<return_type_full_name>System.String</return_type_full_name>
			</feature>
			<feature>
				<feature_modified>False</feature_modified>
				<frozen_feature>False</frozen_feature>
				<static>False</static>
				<abstract>False</abstract>
				<method>True</method>
				<field>False</field>
				<creation_routine>False</creation_routine>
				<prefix>False</prefix>
				<infix>False</infix>
				<new_slot>True</new_slot>
				<enum_literal>False</enum_literal>
				<is_literal>False</is_literal>
				<feature_eiffel_name>add_attribute_string_string_html_text_writer_attribute</feature_eiffel_name>
				<feature_external_name>AddAttribute</feature_external_name>
				<arguments>
					<argument>
						<argument_eiffel_name>name</argument_eiffel_name>
						<argument_external_name>name</argument_external_name>
						<argument_type>STRING</argument_type>
						<argument_type_full_name>System.String</argument_type_full_name>
					</argument>
					<argument>
						<argument_eiffel_name>value</argument_eiffel_name>
						<argument_external_name>value</argument_external_name>
						<argument_type>STRING</argument_type>
						<argument_type_full_name>System.String</argument_type_full_name>
					</argument>
					<argument>
						<argument_eiffel_name>key</argument_eiffel_name>
						<argument_external_name>key</argument_external_name>
						<argument_type>SYSTEM_WEB_UI_HTMLTEXTWRITERATTRIBUTE</argument_type>
						<argument_type_full_name>System.Web.UI.HtmlTextWriterAttribute</argument_type_full_name>
					</argument>
				</arguments>
				<return_type />
				<return_type_full_name>System.Void</return_type_full_name>
			</feature>
			<feature>
				<feature_modified>False</feature_modified>
				<frozen_feature>True</frozen_feature>
				<static>False</static>
				<abstract>False</abstract>
				<method>True</method>
				<field>False</field>
				<creation_routine>False</creation_routine>
				<prefix>False</prefix>
				<infix>False</infix>
				<new_slot>True</new_slot>
				<enum_literal>False</enum_literal>
				<is_literal>False</is_literal>
				<feature_eiffel_name>push_end_tag</feature_eiffel_name>
				<feature_external_name>PushEndTag</feature_external_name>
				<arguments>
					<argument>
						<argument_eiffel_name>end_tag</argument_eiffel_name>
						<argument_external_name>endTag</argument_external_name>
						<argument_type>STRING</argument_type>
						<argument_type_full_name>System.String</argument_type_full_name>
					</argument>
				</arguments>
				<return_type />
				<return_type_full_name>System.Void</return_type_full_name>
			</feature>
			<feature>
				<feature_modified>False</feature_modified>
				<frozen_feature>True</frozen_feature>
				<static>True</static>
				<abstract>False</abstract>
				<method>True</method>
				<field>False</field>
				<creation_routine>False</creation_routine>
				<prefix>False</prefix>
				<infix>False</infix>
				<new_slot>True</new_slot>
				<enum_literal>False</enum_literal>
				<is_literal>False</is_literal>
				<feature_eiffel_name>register_style</feature_eiffel_name>
				<feature_external_name>RegisterStyle</feature_external_name>
				<arguments>
					<argument>
						<argument_eiffel_name>name</argument_eiffel_name>
						<argument_external_name>name</argument_external_name>
						<argument_type>STRING</argument_type>
						<argument_type_full_name>System.String</argument_type_full_name>
					</argument>
					<argument>
						<argument_eiffel_name>key</argument_eiffel_name>
						<argument_external_name>key</argument_external_name>
						<argument_type>SYSTEM_WEB_UI_HTMLTEXTWRITERSTYLE</argument_type>
						<argument_type_full_name>System.Web.UI.HtmlTextWriterStyle</argument_type_full_name>
					</argument>
				</arguments>
				<return_type />
				<return_type_full_name>System.Void</return_type_full_name>
			</feature>
			<feature>
				<feature_modified>False</feature_modified>
				<frozen_feature>False</frozen_feature>
				<static>False</static>
				<abstract>False</abstract>
				<method>True</method>
				<field>False</field>
				<creation_routine>False</creation_routine>
				<prefix>False</prefix>
				<infix>False</infix>
				<new_slot>True</new_slot>
				<enum_literal>False</enum_literal>
				<is_literal>False</is_literal>
				<feature_eiffel_name>render_before_content</feature_eiffel_name>
				<feature_external_name>RenderBeforeContent</feature_external_name>
				<return_type>STRING</return_type>
				<return_type_full_name>System.String</return_type_full_name>
			</feature>
			<feature>
				<feature_modified>False</feature_modified>
				<frozen_feature>False</frozen_feature>
				<static>False</static>
				<abstract>False</abstract>
				<method>True</method>
				<field>False</field>
				<creation_routine>False</creation_routine>
				<prefix>False</prefix>
				<infix>False</infix>
				<new_slot>True</new_slot>
				<enum_literal>False</enum_literal>
				<is_literal>False</is_literal>
				<feature_eiffel_name>on_tag_render</feature_eiffel_name>
				<feature_external_name>OnTagRender</feature_external_name>
				<arguments>
					<argument>
						<argument_eiffel_name>name</argument_eiffel_name>
						<argument_external_name>name</argument_external_name>
						<argument_type>STRING</argument_type>
						<argument_type_full_name>System.String</argument_type_full_name>
					</argument>
					<argument>
						<argument_eiffel_name>key</argument_eiffel_name>
						<argument_external_name>key</argument_external_name>
						<argument_type>SYSTEM_WEB_UI_HTMLTEXTWRITERTAG</argument_type>
						<argument_type_full_name>System.Web.UI.HtmlTextWriterTag</argument_type_full_name>
					</argument>
				</arguments>
				<return_type>BOOLEAN</return_type>
				<return_type_full_name>System.Boolean</return_type_full_name>
			</feature>
			<feature>
				<feature_modified>False</feature_modified>
				<frozen_feature>True</frozen_feature>
				<static>False</static>
				<abstract>False</abstract>
				<method>True</method>
				<field>False</field>
				<creation_routine>False</creation_routine>
				<prefix>False</prefix>
				<infix>False</infix>
				<new_slot>True</new_slot>
				<enum_literal>False</enum_literal>
				<is_literal>False</is_literal>
				<feature_eiffel_name>set_tag_key</feature_eiffel_name>
				<feature_external_name>set_TagKey</feature_external_name>
				<arguments>
					<argument>
						<argument_eiffel_name>value</argument_eiffel_name>
						<argument_external_name>value</argument_external_name>
						<argument_type>SYSTEM_WEB_UI_HTMLTEXTWRITERTAG</argument_type>
						<argument_type_full_name>System.Web.UI.HtmlTextWriterTag</argument_type_full_name>
					</argument>
				</arguments>
				<return_type />
				<return_type_full_name>System.Void</return_type_full_name>
			</feature>
			<feature>
				<feature_modified>False</feature_modified>
				<frozen_feature>True</frozen_feature>
				<static>False</static>
				<abstract>False</abstract>
				<method>True</method>
				<field>False</field>
				<creation_routine>False</creation_routine>
				<prefix>False</prefix>
				<infix>False</infix>
				<new_slot>True</new_slot>
				<enum_literal>False</enum_literal>
				<is_literal>False</is_literal>
				<feature_eiffel_name>get_tag_name</feature_eiffel_name>
				<feature_external_name>get_TagName</feature_external_name>
				<return_type>STRING</return_type>
				<return_type_full_name>System.String</return_type_full_name>
			</feature>
			<feature>
				<feature_modified>False</feature_modified>
				<frozen_feature>True</frozen_feature>
				<static>True</static>
				<abstract>False</abstract>
				<method>True</method>
				<field>False</field>
				<creation_routine>False</creation_routine>
				<prefix>False</prefix>
				<infix>False</infix>
				<new_slot>True</new_slot>
				<enum_literal>False</enum_literal>
				<is_literal>False</is_literal>
				<feature_eiffel_name>register_tag</feature_eiffel_name>
				<feature_external_name>RegisterTag</feature_external_name>
				<arguments>
					<argument>
						<argument_eiffel_name>name</argument_eiffel_name>
						<argument_external_name>name</argument_external_name>
						<argument_type>STRING</argument_type>
						<argument_type_full_name>System.String</argument_type_full_name>
					</argument>
					<argument>
						<argument_eiffel_name>key</argument_eiffel_name>
						<argument_external_name>key</argument_external_name>
						<argument_type>SYSTEM_WEB_UI_HTMLTEXTWRITERTAG</argument_type>
						<argument_type_full_name>System.Web.UI.HtmlTextWriterTag</argument_type_full_name>
					</argument>
				</arguments>
				<return_type />
				<return_type_full_name>System.Void</return_type_full_name>
			</feature>
			<feature>
				<feature_modified>False</feature_modified>
				<frozen_feature>False</frozen_feature>
				<static>False</static>
				<abstract>False</abstract>
				<method>True</method>
				<field>False</field>
				<creation_routine>False</creation_routine>
				<prefix>False</prefix>
				<infix>False</infix>
				<new_slot>True</new_slot>
				<enum_literal>False</enum_literal>
				<is_literal>False</is_literal>
				<feature_eiffel_name>encode_attribute_value_html_text_writer_attribute</feature_eiffel_name>
				<feature_external_name>EncodeAttributeValue</feature_external_name>
				<arguments>
					<argument>
						<argument_eiffel_name>attr_key</argument_eiffel_name>
						<argument_external_name>attrKey</argument_external_name>
						<argument_type>SYSTEM_WEB_UI_HTMLTEXTWRITERATTRIBUTE</argument_type>
						<argument_type_full_name>System.Web.UI.HtmlTextWriterAttribute</argument_type_full_name>
					</argument>
					<argument>
						<argument_eiffel_name>value</argument_eiffel_name>
						<argument_external_name>value</argument_external_name>
						<argument_type>STRING</argument_type>
						<argument_type_full_name>System.String</argument_type_full_name>
					</argument>
				</arguments>
				<return_type>STRING</return_type>
				<return_type_full_name>System.String</return_type_full_name>
			</feature>
			<feature>
				<feature_modified>False</feature_modified>
				<frozen_feature>False</frozen_feature>
				<static>False</static>
				<abstract>False</abstract>
				<method>True</method>
				<field>False</field>
				<creation_routine>False</creation_routine>
				<prefix>False</prefix>
				<infix>False</infix>
				<new_slot>True</new_slot>
				<enum_literal>False</enum_literal>
				<is_literal>False</is_literal>
				<feature_eiffel_name>add_style_attribute_string_string_html_text_writer_style</feature_eiffel_name>
				<feature_external_name>AddStyleAttribute</feature_external_name>
				<arguments>
					<argument>
						<argument_eiffel_name>name</argument_eiffel_name>
						<argument_external_name>name</argument_external_name>
						<argument_type>STRING</argument_type>
						<argument_type_full_name>System.String</argument_type_full_name>
					</argument>
					<argument>
						<argument_eiffel_name>value</argument_eiffel_name>
						<argument_external_name>value</argument_external_name>
						<argument_type>STRING</argument_type>
						<argument_type_full_name>System.String</argument_type_full_name>
					</argument>
					<argument>
						<argument_eiffel_name>key</argument_eiffel_name>
						<argument_external_name>key</argument_external_name>
						<argument_type>SYSTEM_WEB_UI_HTMLTEXTWRITERSTYLE</argument_type>
						<argument_type_full_name>System.Web.UI.HtmlTextWriterStyle</argument_type_full_name>
					</argument>
				</arguments>
				<return_type />
				<return_type_full_name>System.Void</return_type_full_name>
			</feature>
			<feature>
				<feature_modified>False</feature_modified>
				<frozen_feature>False</frozen_feature>
				<static>False</static>
				<abstract>False</abstract>
				<method>True</method>
				<field>False</field>
				<creation_routine>False</creation_routine>
				<prefix>False</prefix>
				<infix>False</infix>
				<new_slot>True</new_slot>
				<enum_literal>False</enum_literal>
				<is_literal>False</is_literal>
				<feature_eiffel_name>output_tabs</feature_eiffel_name>
				<feature_external_name>OutputTabs</feature_external_name>
				<return_type />
				<return_type_full_name>System.Void</return_type_full_name>
			</feature>
			<feature>
				<feature_modified>False</feature_modified>
				<frozen_feature>True</frozen_feature>
				<static>False</static>
				<abstract>False</abstract>
				<method>True</method>
				<field>False</field>
				<creation_routine>False</creation_routine>
				<prefix>False</prefix>
				<infix>False</infix>
				<new_slot>True</new_slot>
				<enum_literal>False</enum_literal>
				<is_literal>False</is_literal>
				<feature_eiffel_name>is_style_attribute_defined_html_text_writer_style_string</feature_eiffel_name>
				<feature_external_name>IsStyleAttributeDefined</feature_external_name>
				<arguments>
					<argument>
						<argument_eiffel_name>key</argument_eiffel_name>
						<argument_external_name>key</argument_external_name>
						<argument_type>SYSTEM_WEB_UI_HTMLTEXTWRITERSTYLE</argument_type>
						<argument_type_full_name>System.Web.UI.HtmlTextWriterStyle</argument_type_full_name>
					</argument>
					<argument>
						<argument_eiffel_name>value</argument_eiffel_name>
						<argument_external_name>value</argument_external_name>
						<argument_type>STRING</argument_type>
						<argument_type_full_name>System.String&amp;</argument_type_full_name>
					</argument>
				</arguments>
				<return_type>BOOLEAN</return_type>
				<return_type_full_name>System.Boolean</return_type_full_name>
			</feature>
			<feature>
				<feature_modified>False</feature_modified>
				<frozen_feature>True</frozen_feature>
				<static>False</static>
				<abstract>False</abstract>
				<method>True</method>
				<field>False</field>
				<creation_routine>False</creation_routine>
				<prefix>False</prefix>
				<infix>False</infix>
				<new_slot>True</new_slot>
				<enum_literal>False</enum_literal>
				<is_literal>False</is_literal>
				<feature_eiffel_name>is_style_attribute_defined</feature_eiffel_name>
				<feature_external_name>IsStyleAttributeDefined</feature_external_name>
				<arguments>
					<argument>
						<argument_eiffel_name>key</argument_eiffel_name>
						<argument_external_name>key</argument_external_name>
						<argument_type>SYSTEM_WEB_UI_HTMLTEXTWRITERSTYLE</argument_type>
						<argument_type_full_name>System.Web.UI.HtmlTextWriterStyle</argument_type_full_name>
					</argument>
				</arguments>
				<return_type>BOOLEAN</return_type>
				<return_type_full_name>System.Boolean</return_type_full_name>
			</feature>
			<feature>
				<feature_modified>False</feature_modified>
				<frozen_feature>True</frozen_feature>
				<static>False</static>
				<abstract>False</abstract>
				<method>True</method>
				<field>False</field>
				<creation_routine>False</creation_routine>
				<prefix>False</prefix>
				<infix>False</infix>
				<new_slot>True</new_slot>
				<enum_literal>False</enum_literal>
				<is_literal>False</is_literal>
				<feature_eiffel_name>get_tag_key</feature_eiffel_name>
				<feature_external_name>get_TagKey</feature_external_name>
				<return_type>SYSTEM_WEB_UI_HTMLTEXTWRITERTAG</return_type>
				<return_type_full_name>System.Web.UI.HtmlTextWriterTag</return_type_full_name>
			</feature>
			<feature>
				<feature_modified>False</feature_modified>
				<frozen_feature>True</frozen_feature>
				<static>False</static>
				<abstract>False</abstract>
				<method>True</method>
				<field>False</field>
				<creation_routine>False</creation_routine>
				<prefix>False</prefix>
				<infix>False</infix>
				<new_slot>True</new_slot>
				<enum_literal>False</enum_literal>
				<is_literal>False</is_literal>
				<feature_eiffel_name>is_attribute_defined_html_text_writer_attribute_string</feature_eiffel_name>
				<feature_external_name>IsAttributeDefined</feature_external_name>
				<arguments>
					<argument>
						<argument_eiffel_name>key</argument_eiffel_name>
						<argument_external_name>key</argument_external_name>
						<argument_type>SYSTEM_WEB_UI_HTMLTEXTWRITERATTRIBUTE</argument_type>
						<argument_type_full_name>System.Web.UI.HtmlTextWriterAttribute</argument_type_full_name>
					</argument>
					<argument>
						<argument_eiffel_name>value</argument_eiffel_name>
						<argument_external_name>value</argument_external_name>
						<argument_type>STRING</argument_type>
						<argument_type_full_name>System.String&amp;</argument_type_full_name>
					</argument>
				</arguments>
				<return_type>BOOLEAN</return_type>
				<return_type_full_name>System.Boolean</return_type_full_name>
			</feature>
			<feature>
				<feature_modified>False</feature_modified>
				<frozen_feature>True</frozen_feature>
				<static>False</static>
				<abstract>False</abstract>
				<method>True</method>
				<field>False</field>
				<creation_routine>False</creation_routine>
				<prefix>False</prefix>
				<infix>False</infix>
				<new_slot>True</new_slot>
				<enum_literal>False</enum_literal>
				<is_literal>False</is_literal>
				<feature_eiffel_name>is_attribute_defined</feature_eiffel_name>
				<feature_external_name>IsAttributeDefined</feature_external_name>
				<arguments>
					<argument>
						<argument_eiffel_name>key</argument_eiffel_name>
						<argument_external_name>key</argument_external_name>
						<argument_type>SYSTEM_WEB_UI_HTMLTEXTWRITERATTRIBUTE</argument_type>
						<argument_type_full_name>System.Web.UI.HtmlTextWriterAttribute</argument_type_full_name>
					</argument>
				</arguments>
				<return_type>BOOLEAN</return_type>
				<return_type_full_name>System.Boolean</return_type_full_name>
			</feature>
			<feature>
				<feature_modified>False</feature_modified>
				<frozen_feature>False</frozen_feature>
				<static>False</static>
				<abstract>False</abstract>
				<method>True</method>
				<field>False</field>
				<creation_routine>False</creation_routine>
				<prefix>False</prefix>
				<infix>False</infix>
				<new_slot>True</new_slot>
				<enum_literal>False</enum_literal>
				<is_literal>False</is_literal>
				<feature_eiffel_name>render_before_tag</feature_eiffel_name>
				<feature_external_name>RenderBeforeTag</feature_external_name>
				<return_type>STRING</return_type>
				<return_type_full_name>System.String</return_type_full_name>
			</feature>
			<feature>
				<feature_modified>False</feature_modified>
				<frozen_feature>True</frozen_feature>
				<static>False</static>
				<abstract>False</abstract>
				<method>True</method>
				<field>False</field>
				<creation_routine>False</creation_routine>
				<prefix>False</prefix>
				<infix>False</infix>
				<new_slot>True</new_slot>
				<enum_literal>False</enum_literal>
				<is_literal>False</is_literal>
				<feature_eiffel_name>pop_end_tag</feature_eiffel_name>
				<feature_external_name>PopEndTag</feature_external_name>
				<return_type>STRING</return_type>
				<return_type_full_name>System.String</return_type_full_name>
			</feature>
			<feature>
				<feature_modified>False</feature_modified>
				<frozen_feature>True</frozen_feature>
				<static>False</static>
				<abstract>False</abstract>
				<method>True</method>
				<field>False</field>
				<creation_routine>False</creation_routine>
				<prefix>False</prefix>
				<infix>False</infix>
				<new_slot>True</new_slot>
				<enum_literal>False</enum_literal>
				<is_literal>False</is_literal>
				<feature_eiffel_name>get_style_name</feature_eiffel_name>
				<feature_external_name>GetStyleName</feature_external_name>
				<arguments>
					<argument>
						<argument_eiffel_name>style_key</argument_eiffel_name>
						<argument_external_name>styleKey</argument_external_name>
						<argument_type>SYSTEM_WEB_UI_HTMLTEXTWRITERSTYLE</argument_type>
						<argument_type_full_name>System.Web.UI.HtmlTextWriterStyle</argument_type_full_name>
					</argument>
				</arguments>
				<return_type>STRING</return_type>
				<return_type_full_name>System.String</return_type_full_name>
			</feature>
			<feature>
				<feature_modified>False</feature_modified>
				<frozen_feature>True</frozen_feature>
				<static>False</static>
				<abstract>False</abstract>
				<method>True</method>
				<field>False</field>
				<creation_routine>False</creation_routine>
				<prefix>False</prefix>
				<infix>False</infix>
				<new_slot>True</new_slot>
				<enum_literal>False</enum_literal>
				<is_literal>False</is_literal>
				<feature_eiffel_name>get_attribute_key</feature_eiffel_name>
				<feature_external_name>GetAttributeKey</feature_external_name>
				<arguments>
					<argument>
						<argument_eiffel_name>attr_name</argument_eiffel_name>
						<argument_external_name>attrName</argument_external_name>
						<argument_type>STRING</argument_type>
						<argument_type_full_name>System.String</argument_type_full_name>
					</argument>
				</arguments>
				<return_type>SYSTEM_WEB_UI_HTMLTEXTWRITERATTRIBUTE</return_type>
				<return_type_full_name>System.Web.UI.HtmlTextWriterAttribute</return_type_full_name>
			</feature>
			<feature>
				<feature_modified>False</feature_modified>
				<frozen_feature>False</frozen_feature>
				<static>False</static>
				<abstract>False</abstract>
				<method>True</method>
				<field>False</field>
				<creation_routine>False</creation_routine>
				<prefix>False</prefix>
				<infix>False</infix>
				<new_slot>True</new_slot>
				<enum_literal>False</enum_literal>
				<is_literal>False</is_literal>
				<feature_eiffel_name>filter_attributes</feature_eiffel_name>
				<feature_external_name>FilterAttributes</feature_external_name>
				<return_type />
				<return_type_full_name>System.Void</return_type_full_name>
			</feature>
			<feature>
				<feature_modified>False</feature_modified>
				<frozen_feature>False</frozen_feature>
				<static>False</static>
				<abstract>False</abstract>
				<method>True</method>
				<field>False</field>
				<creation_routine>False</creation_routine>
				<prefix>False</prefix>
				<infix>False</infix>
				<new_slot>True</new_slot>
				<enum_literal>False</enum_literal>
				<is_literal>False</is_literal>
				<feature_eiffel_name>render_after_content</feature_eiffel_name>
				<feature_external_name>RenderAfterContent</feature_external_name>
				<return_type>STRING</return_type>
				<return_type_full_name>System.String</return_type_full_name>
			</feature>
			<feature>
				<feature_modified>False</feature_modified>
				<frozen_feature>True</frozen_feature>
				<static>False</static>
				<abstract>False</abstract>
				<method>True</method>
				<field>False</field>
				<creation_routine>False</creation_routine>
				<prefix>False</prefix>
				<infix>False</infix>
				<new_slot>True</new_slot>
				<enum_literal>False</enum_literal>
				<is_literal>False</is_literal>
				<feature_eiffel_name>set_tag_name</feature_eiffel_name>
				<feature_external_name>set_TagName</feature_external_name>
				<arguments>
					<argument>
						<argument_eiffel_name>value</argument_eiffel_name>
						<argument_external_name>value</argument_external_name>
						<argument_type>STRING</argument_type>
						<argument_type_full_name>System.String</argument_type_full_name>
					</argument>
				</arguments>
				<return_type />
				<return_type_full_name>System.Void</return_type_full_name>
			</feature>
			<feature>
				<feature_modified>False</feature_modified>
				<frozen_feature>True</frozen_feature>
				<static>False</static>
				<abstract>False</abstract>
				<method>True</method>
				<field>False</field>
				<creation_routine>False</creation_routine>
				<prefix>False</prefix>
				<infix>False</infix>
				<new_slot>True</new_slot>
				<enum_literal>False</enum_literal>
				<is_literal>False</is_literal>
				<feature_eiffel_name>encode_attribute_value</feature_eiffel_name>
				<feature_external_name>EncodeAttributeValue</feature_external_name>
				<arguments>
					<argument>
						<argument_eiffel_name>value</argument_eiffel_name>
						<argument_external_name>value</argument_external_name>
						<argument_type>STRING</argument_type>
						<argument_type_full_name>System.String</argument_type_full_name>
					</argument>
					<argument>
						<argument_eiffel_name>f_encode</argument_eiffel_name>
						<argument_external_name>fEncode</argument_external_name>
						<argument_type>BOOLEAN</argument_type>
						<argument_type_full_name>System.Boolean</argument_type_full_name>
					</argument>
				</arguments>
				<return_type>STRING</return_type>
				<return_type_full_name>System.String</return_type_full_name>
			</feature>
			<feature>
				<feature_modified>False</feature_modified>
				<frozen_feature>False</frozen_feature>
				<static>False</static>
				<abstract>False</abstract>
				<method>True</method>
				<field>False</field>
				<creation_routine>False</creation_routine>
				<prefix>False</prefix>
				<infix>False</infix>
				<new_slot>True</new_slot>
				<enum_literal>False</enum_literal>
				<is_literal>False</is_literal>
				<feature_eiffel_name>get_tag_name_html_text_writer_tag</feature_eiffel_name>
				<feature_external_name>GetTagName</feature_external_name>
				<arguments>
					<argument>
						<argument_eiffel_name>tag_key</argument_eiffel_name>
						<argument_external_name>tagKey</argument_external_name>
						<argument_type>SYSTEM_WEB_UI_HTMLTEXTWRITERTAG</argument_type>
						<argument_type_full_name>System.Web.UI.HtmlTextWriterTag</argument_type_full_name>
					</argument>
				</arguments>
				<return_type>STRING</return_type>
				<return_type_full_name>System.String</return_type_full_name>
			</feature>
			<feature>
				<feature_modified>False</feature_modified>
				<frozen_feature>False</frozen_feature>
				<static>False</static>
				<abstract>False</abstract>
				<method>True</method>
				<field>False</field>
				<creation_routine>False</creation_routine>
				<prefix>False</prefix>
				<infix>False</infix>
				<new_slot>True</new_slot>
				<enum_literal>False</enum_literal>
				<is_literal>False</is_literal>
				<feature_eiffel_name>render_after_tag</feature_eiffel_name>
				<feature_external_name>RenderAfterTag</feature_external_name>
				<return_type>STRING</return_type>
				<return_type_full_name>System.String</return_type_full_name>
			</feature>
			<feature>
				<feature_modified>False</feature_modified>
				<frozen_feature>False</frozen_feature>
				<static>False</static>
				<abstract>False</abstract>
				<method>True</method>
				<field>False</field>
				<creation_routine>False</creation_routine>
				<prefix>False</prefix>
				<infix>False</infix>
				<new_slot>True</new_slot>
				<enum_literal>False</enum_literal>
				<is_literal>False</is_literal>
				<feature_eiffel_name>on_attribute_render</feature_eiffel_name>
				<feature_external_name>OnAttributeRender</feature_external_name>
				<arguments>
					<argument>
						<argument_eiffel_name>name</argument_eiffel_name>
						<argument_external_name>name</argument_external_name>
						<argument_type>STRING</argument_type>
						<argument_type_full_name>System.String</argument_type_full_name>
					</argument>
					<argument>
						<argument_eiffel_name>value</argument_eiffel_name>
						<argument_external_name>value</argument_external_name>
						<argument_type>STRING</argument_type>
						<argument_type_full_name>System.String</argument_type_full_name>
					</argument>
					<argument>
						<argument_eiffel_name>key</argument_eiffel_name>
						<argument_external_name>key</argument_external_name>
						<argument_type>SYSTEM_WEB_UI_HTMLTEXTWRITERATTRIBUTE</argument_type>
						<argument_type_full_name>System.Web.UI.HtmlTextWriterAttribute</argument_type_full_name>
					</argument>
				</arguments>
				<return_type>BOOLEAN</return_type>
				<return_type_full_name>System.Boolean</return_type_full_name>
			</feature>
			<feature>
				<feature_modified>False</feature_modified>
				<frozen_feature>True</frozen_feature>
				<static>True</static>
				<abstract>False</abstract>
				<method>True</method>
				<field>False</field>
				<creation_routine>False</creation_routine>
				<prefix>False</prefix>
				<infix>False</infix>
				<new_slot>True</new_slot>
				<enum_literal>False</enum_literal>
				<is_literal>False</is_literal>
				<feature_eiffel_name>register_attribute</feature_eiffel_name>
				<feature_external_name>RegisterAttribute</feature_external_name>
				<arguments>
					<argument>
						<argument_eiffel_name>name</argument_eiffel_name>
						<argument_external_name>name</argument_external_name>
						<argument_type>STRING</argument_type>
						<argument_type_full_name>System.String</argument_type_full_name>
					</argument>
					<argument>
						<argument_eiffel_name>key</argument_eiffel_name>
						<argument_external_name>key</argument_external_name>
						<argument_type>SYSTEM_WEB_UI_HTMLTEXTWRITERATTRIBUTE</argument_type>
						<argument_type_full_name>System.Web.UI.HtmlTextWriterAttribute</argument_type_full_name>
					</argument>
				</arguments>
				<return_type />
				<return_type_full_name>System.Void</return_type_full_name>
			</feature>
			<feature>
				<feature_modified>False</feature_modified>
				<frozen_feature>False</frozen_feature>
				<static>False</static>
				<abstract>False</abstract>
				<method>True</method>
				<field>False</field>
				<creation_routine>False</creation_routine>
				<prefix>False</prefix>
				<infix>False</infix>
				<new_slot>True</new_slot>
				<enum_literal>False</enum_literal>
				<is_literal>False</is_literal>
				<feature_eiffel_name>on_style_attribute_render</feature_eiffel_name>
				<feature_external_name>OnStyleAttributeRender</feature_external_name>
				<arguments>
					<argument>
						<argument_eiffel_name>name</argument_eiffel_name>
						<argument_external_name>name</argument_external_name>
						<argument_type>STRING</argument_type>
						<argument_type_full_name>System.String</argument_type_full_name>
					</argument>
					<argument>
						<argument_eiffel_name>value</argument_eiffel_name>
						<argument_external_name>value</argument_external_name>
						<argument_type>STRING</argument_type>
						<argument_type_full_name>System.String</argument_type_full_name>
					</argument>
					<argument>
						<argument_eiffel_name>key</argument_eiffel_name>
						<argument_external_name>key</argument_external_name>
						<argument_type>SYSTEM_WEB_UI_HTMLTEXTWRITERSTYLE</argument_type>
						<argument_type_full_name>System.Web.UI.HtmlTextWriterStyle</argument_type_full_name>
					</argument>
				</arguments>
				<return_type>BOOLEAN</return_type>
				<return_type_full_name>System.Boolean</return_type_full_name>
			</feature>
		</implementation>
		<bit_or_infix>False</bit_or_infix>
	</body>
</class>