<!DOCTYPE type SYSTEM "../type.dtd">
<class>
	<header>
		<modified>False</modified>
		<frozen>False</frozen>
		<expanded>False</expanded>
		<deferred>True</deferred>
		<generic>False</generic>
		<class_eiffel_name>SYSTEM_RUNTIME_REMOTING_ACTIVATION_IREMOTINGDISPATCHER</class_eiffel_name>
		<alias>
			<simple_name>IRemotingDispatcher</simple_name>
			<namespace>System.Runtime.Remoting.Activation</namespace>
			<assembly_name>System.Runtime.Remoting</assembly_name>
			<assembly_version>1.0.2411.0</assembly_version>
			<assembly_culture>neutral</assembly_culture>
			<assembly_public_key>b77a5c561934e089</assembly_public_key>
		</alias>
		<inherit>
			<parent>
				<parent_name>ANY</parent_name>
				<undefine>finalize, get_hash_code, is_equal, to_string</undefine>
			</parent>
		</inherit>
		<create_none>False</create_none>
	</header>
	<body>
		<basic_operations>
			<feature>
				<feature_modified>False</feature_modified>
				<frozen_feature>False</frozen_feature>
				<static>False</static>
				<abstract>True</abstract>
				<method>True</method>
				<field>False</field>
				<creation_routine>False</creation_routine>
				<prefix>False</prefix>
				<infix>False</infix>
				<new_slot>True</new_slot>
				<enum_literal>False</enum_literal>
				<is_literal>False</is_literal>
				<feature_eiffel_name>do_gccollect</feature_eiffel_name>
				<feature_external_name>DoGCCollect</feature_external_name>
				<return_type />
				<return_type_full_name>System.Void</return_type_full_name>
			</feature>
			<feature>
				<feature_modified>False</feature_modified>
				<frozen_feature>False</frozen_feature>
				<static>False</static>
				<abstract>True</abstract>
				<method>True</method>
				<field>False</field>
				<creation_routine>False</creation_routine>
				<prefix>False</prefix>
				<infix>False</infix>
				<new_slot>True</new_slot>
				<enum_literal>False</enum_literal>
				<is_literal>False</is_literal>
				<feature_eiffel_name>request_configure_remoting</feature_eiffel_name>
				<feature_external_name>RequestConfigureRemoting</feature_external_name>
				<arguments>
					<argument>
						<argument_eiffel_name>full_config_file_name</argument_eiffel_name>
						<argument_external_name>fullConfigFileName</argument_external_name>
						<argument_type>STRING</argument_type>
						<argument_type_full_name>System.String</argument_type_full_name>
					</argument>
				</arguments>
				<return_type>INTEGER</return_type>
				<return_type_full_name>System.Int32</return_type_full_name>
			</feature>
			<feature>
				<feature_modified>False</feature_modified>
				<frozen_feature>False</frozen_feature>
				<static>False</static>
				<abstract>True</abstract>
				<method>True</method>
				<field>False</field>
				<creation_routine>False</creation_routine>
				<prefix>False</prefix>
				<infix>False</infix>
				<new_slot>True</new_slot>
				<enum_literal>False</enum_literal>
				<is_literal>False</is_literal>
				<feature_eiffel_name>stop_processing</feature_eiffel_name>
				<feature_external_name>StopProcessing</feature_external_name>
				<return_type />
				<return_type_full_name>System.Void</return_type_full_name>
			</feature>
			<feature>
				<feature_modified>False</feature_modified>
				<frozen_feature>False</frozen_feature>
				<static>False</static>
				<abstract>True</abstract>
				<method>True</method>
				<field>False</field>
				<creation_routine>False</creation_routine>
				<prefix>False</prefix>
				<infix>False</infix>
				<new_slot>True</new_slot>
				<enum_literal>False</enum_literal>
				<is_literal>False</is_literal>
				<feature_eiffel_name>start_processing</feature_eiffel_name>
				<feature_external_name>StartProcessing</feature_external_name>
				<return_type />
				<return_type_full_name>System.Void</return_type_full_name>
			</feature>
			<feature>
				<feature_modified>False</feature_modified>
				<frozen_feature>False</frozen_feature>
				<static>False</static>
				<abstract>True</abstract>
				<method>True</method>
				<field>False</field>
				<creation_routine>False</creation_routine>
				<prefix>False</prefix>
				<infix>False</infix>
				<new_slot>True</new_slot>
				<enum_literal>False</enum_literal>
				<is_literal>False</is_literal>
				<feature_eiffel_name>process_request</feature_eiffel_name>
				<feature_external_name>ProcessRequest</feature_external_name>
				<arguments>
					<argument>
						<argument_eiffel_name>url</argument_eiffel_name>
						<argument_external_name>url</argument_external_name>
						<argument_type>STRING</argument_type>
						<argument_type_full_name>System.String</argument_type_full_name>
					</argument>
					<argument>
						<argument_eiffel_name>cb_request_hdr_data</argument_eiffel_name>
						<argument_external_name>cbRequestHdrData</argument_external_name>
						<argument_type>INTEGER</argument_type>
						<argument_type_full_name>System.Int32</argument_type_full_name>
					</argument>
					<argument>
						<argument_eiffel_name>request_headers_and_body</argument_eiffel_name>
						<argument_external_name>requestHeadersAndBody</argument_external_name>
						<argument_type>ARRAY [INTEGER_8]</argument_type>
						<argument_type_full_name>System.Byte[]</argument_type_full_name>
					</argument>
					<argument>
						<argument_eiffel_name>cb_response_hdr_data</argument_eiffel_name>
						<argument_external_name>cbResponseHdrData</argument_external_name>
						<argument_type>INTEGER</argument_type>
						<argument_type_full_name>System.Int32&amp;</argument_type_full_name>
					</argument>
					<argument>
						<argument_eiffel_name>response_headers_and_body</argument_eiffel_name>
						<argument_external_name>responseHeadersAndBody</argument_external_name>
						<argument_type>ARRAY [INTEGER_8]</argument_type>
						<argument_type_full_name>System.Byte[]&amp;</argument_type_full_name>
					</argument>
				</arguments>
				<return_type>INTEGER</return_type>
				<return_type_full_name>System.Int32</return_type_full_name>
			</feature>
		</basic_operations>
		<bit_or_infix>False</bit_or_infix>
	</body>
</class>
