<document title="Select the Compilation mode" output="studio">
	<meta_data/>
	<paragraph>
		<paragraph>The first screen of the wizard lets you specify the mode in which the profiled system was compiled.</paragraph>
		<paragraph>If you have run a finalized system under the control of the profiler then select 
			<bold>Finalized mode</bold> and click 
			<bold>Next</bold>. On the contrary if you have executed the system in Workbench mode then select 
			<bold>Workbench mode</bold> and click 
			<bold>Next</bold>.
		</paragraph>
		<line_break/>
		<image>
			<url>/images/eiffelstudio/dialogs_and_wizards/profiler_wizard_first_state.png</url>
		</image> 
		<line_break/>
		<line_break/>
		<paragraph>Clicking 
			<bold>Next</bold> will lead you to the 
			<link>
				<url>20_second_state.xml</url>
				<label>Second state</label>
			</link> or to the 
			<link>
				<url>30_third_state.xml</url>
				<label>Third state</label>
			</link> depending on whether an 
			<italic>Execution Profile</italic> has already been generated for this compilation mode or not. If no 
			<italic>Execution Profile</italic> has been generated so far (which happens the first time you execute this wizard for a specified project in a given compilation mode) youwill go to the 
			<link>
				<url>30_third_state.xml</url>
				<label>Third state</label>
			</link>, otherwise you will go to the 
			<link>
				<url>20_second_state.xml</url>
				<label>Second state</label>
			</link>.
		</paragraph>
		<line_break/>
		<seealso>
			<bold>See Also</bold>
			<line_break/>
			<link>
				<url>../00_introduction.xml</url> 
			</link>
			<link>
				<url>../../../../how_to_s/50_running_and_debugging/70_profiling.xml</url>
				<label>How to profile a system</label>
			</link>
		</seealso>
	</paragraph></document>